{
    "benchmark_version": {
        "benchmarks.Histogram1D.time_histogram1d": "e671e48b4a56eddab60af10f82912a1cba894468a35436c61fadd8f0a42c42ce",
        "benchmarks.Histogram1D.time_histogram1d_weights": "4ce26c3fa2d76232a71eb27de69cdc29c1877457e62f92774b7fd8b6376c6685",
        "benchmarks.Histogram2D.time_histogram2d": "c74f482a09eda4dfdbb5380538077d3477a6a3ecfcbadbe3013737a0fb2602af",
        "benchmarks.Histogram2D.time_histogram2d_weights": "321f640418ab3bae617c5a0d2b53a623adb06091393c79f6adffb711140c0af6"
    },
    "commit_hash": "46b96c1c641c8d8c426a38e0dbdd35e5300a4a1b",
    "date": 1500406273000,
    "ended_at": {
        "benchmarks.Histogram1D.time_histogram1d": 1532044918000,
        "benchmarks.Histogram1D.time_histogram1d_weights": 1532044981000,
        "benchmarks.Histogram2D.time_histogram2d": 1532045076000,
        "benchmarks.Histogram2D.time_histogram2d_weights": 1532045140000
    },
    "env_name": "conda-py3.6-cython-nomkl-numpy1.14",
    "params": {
        "arch": "x86_64",
        "cpu": "Intel(R) Celeron(R) CPU N3450 @ 1.10GHz",
        "cython": "",
        "machine": "oneesk",
        "nomkl": "",
        "numpy": "1.14",
        "os": "Ubuntu 16.04.3 LTS",
        "python": "3.6",
        "ram": "3885480"
    },
    "profiles": {},
    "python": "3.6",
    "requirements": {
        "cython": "",
        "nomkl": "",
        "numpy": "1.14"
    },
    "results": {
        "benchmarks.Histogram1D.time_histogram1d": {
            "params": [
                [
                    "False",
                    "True"
                ],
                [
                    "'>i4'",
                    "'<f4'",
                    "'>f8'",
                    "'<f8'"
                ],
                [
                    "1000.0",
                    "10000.0",
                    "100000.0",
                    "1000000.0",
                    "10000000.0"
                ]
            ],
            "result": [
                0.0002874599800531916,
                0.0005747010740740736,
                0.003719452160714287,
                0.03459904349999998,
                0.3534011500000003,
                0.0002541087748184019,
                0.00040573116431095394,
                0.002031652141509431,
                0.017008944000000005,
                0.16723310449999995,
                0.00026158507976190503,
                0.00042951859765625005,
                0.002501097428571427,
                0.022688788000000005,
                0.22070557150000014,
                0.0002552334976689975,
                0.0003919625465949819,
                0.0021911950510204075,
                0.01947481333333334,
                0.19072239950000003,
                3.4818616666666656e-05,
                0.00012467477611940287,
                0.0012959320301204813,
                0.013235885687500004,
                0.1707231090000001,
                3.0672830141548744e-05,
                9.295672181818179e-05,
                0.0009455919500000001,
                0.00912426791666667,
                0.13438740449999997,
                3.1451445521962334e-05,
                9.777378227272728e-05,
                0.0010374471105769221,
                0.009551985181818181,
                0.14555640049999985,
                2.5979404543197596e-05,
                8.15849233333333e-05,
                0.0007142753486842105,
                0.0066147958125000045,
                0.065127461
            ],
            "stats": [
                {
                    "ci_99": [
                        0.0002868422712765957,
                        0.0002886392659574465
                    ],
                    "max": 0.0002886392659574465,
                    "mean": 0.00028757836037234045,
                    "min": 0.0002868422712765957,
                    "n": 10,
                    "q_25": 0.0002871680026595744,
                    "q_75": 0.0002879220924202128,
                    "std": 5.156067608420503e-07
                },
                {
                    "ci_99": [
                        0.000570746661375662,
                        0.0005765849365079373
                    ],
                    "max": 0.0005765849365079373,
                    "mean": 0.0005739019269841272,
                    "min": 0.000570746661375662,
                    "n": 10,
                    "q_25": 0.0005719600449735449,
                    "q_75": 0.0005752608253968251,
                    "std": 1.983548573921792e-06
                },
                {
                    "ci_99": [
                        0.003709568857142857,
                        0.003742687749999997
                    ],
                    "max": 0.003742687749999997,
                    "mean": 0.0037230233000000008,
                    "min": 0.003709568857142857,
                    "n": 10,
                    "q_25": 0.0037123096160714348,
                    "q_75": 0.0037352025000000006,
                    "std": 1.2294536372908719e-05
                },
                {
                    "ci_99": [
                        0.03455675866666671,
                        0.03483004566666666
                    ],
                    "max": 0.03483004566666666,
                    "mean": 0.034641644,
                    "min": 0.03455675866666671,
                    "n": 8,
                    "q_25": 0.034593198333333325,
                    "q_75": 0.034662005333333336,
                    "std": 8.468483855055343e-05
                },
                null,
                {
                    "ci_99": [
                        0.00025387446246973337,
                        0.00025894940193704616
                    ],
                    "max": 0.00025894940193704616,
                    "mean": 0.00025505483874092014,
                    "min": 0.00025387446246973337,
                    "n": 10,
                    "q_25": 0.00025396787953995163,
                    "q_75": 0.00025557838377724014,
                    "std": 1.6887744445963704e-06
                },
                {
                    "ci_99": [
                        0.0003913877632508832,
                        0.0004126442261484099
                    ],
                    "max": 0.0004126442261484099,
                    "mean": 0.0004042857427561836,
                    "min": 0.0003913877632508832,
                    "n": 10,
                    "q_25": 0.0004044264999999998,
                    "q_75": 0.0004084193975265018,
                    "std": 6.387741472907771e-06
                },
                {
                    "ci_99": [
                        0.0020258423396226424,
                        0.002046423264150945
                    ],
                    "max": 0.002046423264150945,
                    "mean": 0.0020341046226415097,
                    "min": 0.0020258423396226424,
                    "n": 10,
                    "q_25": 0.0020275371415094355,
                    "q_75": 0.002041755641509435,
                    "std": 7.86711127879758e-06
                },
                {
                    "ci_99": [
                        0.0169942448333333,
                        0.017426989333333327
                    ],
                    "max": 0.017426989333333327,
                    "mean": 0.017059192000000004,
                    "min": 0.0169942448333333,
                    "n": 8,
                    "q_25": 0.017005709000000018,
                    "q_75": 0.017012927375000025,
                    "std": 0.00013914687577078368
                },
                {
                    "ci_99": [
                        0.15875237949999588,
                        0.17571382950000403
                    ],
                    "max": 0.16740271900000003,
                    "mean": 0.16723310449999995,
                    "min": 0.16706348999999987,
                    "n": 2,
                    "q_25": 0.1671482972499999,
                    "q_75": 0.16731791175,
                    "std": 0.0001696145000000815
                },
                {
                    "ci_99": [
                        0.0002608326095238095,
                        0.0002667848761904766
                    ],
                    "max": 0.0002667848761904766,
                    "mean": 0.00026228189976190474,
                    "min": 0.0002608326095238095,
                    "n": 10,
                    "q_25": 0.00026141653333333354,
                    "q_75": 0.0002620053714285713,
                    "std": 1.738251882822352e-06
                },
                {
                    "ci_99": [
                        0.00042625427734374957,
                        0.0004321906328124993
                    ],
                    "max": 0.0004321906328124993,
                    "mean": 0.00042962969453125,
                    "min": 0.00042625427734374957,
                    "n": 10,
                    "q_25": 0.00042825799218749994,
                    "q_75": 0.0004313667714843758,
                    "std": 1.9139265594486965e-06
                },
                {
                    "ci_99": [
                        0.002472544047619046,
                        0.0025532247142857145
                    ],
                    "max": 0.0025532247142857145,
                    "mean": 0.002502617066666666,
                    "min": 0.002472544047619046,
                    "n": 10,
                    "q_25": 0.002496847773809523,
                    "q_75": 0.002504184113095239,
                    "std": 2.0014130122359802e-05
                },
                {
                    "ci_99": [
                        0.022367881648833073,
                        0.023624479779738364
                    ],
                    "max": 0.02350875680000004,
                    "mean": 0.022996180714285715,
                    "min": 0.022533229200000005,
                    "n": 7,
                    "q_25": 0.022671068500000002,
                    "q_75": 0.023450176999999982,
                    "std": 0.00041363088857688276
                },
                {
                    "ci_99": [
                        0.20896594650000444,
                        0.23244519649999584
                    ],
                    "max": 0.22094036400000006,
                    "mean": 0.22070557150000014,
                    "min": 0.22047077900000023,
                    "n": 2,
                    "q_25": 0.22058817525000018,
                    "q_75": 0.2208229677500001,
                    "std": 0.00023479249999991403
                },
                {
                    "ci_99": [
                        0.00025501860139860147,
                        0.0002558393333333332
                    ],
                    "max": 0.0002558393333333332,
                    "mean": 0.0002552695529137529,
                    "min": 0.00025501860139860147,
                    "n": 10,
                    "q_25": 0.0002550973613053613,
                    "q_75": 0.00025534277680652685,
                    "std": 2.2537011978163287e-07
                },
                {
                    "ci_99": [
                        0.00039006153046595,
                        0.0003953986666666677
                    ],
                    "max": 0.0003953986666666677,
                    "mean": 0.00039251679247311836,
                    "min": 0.00039006153046595,
                    "n": 10,
                    "q_25": 0.0003911073279569888,
                    "q_75": 0.0003941540788530468,
                    "std": 1.7693049762297183e-06
                },
                {
                    "ci_99": [
                        0.002156342204081633,
                        0.0022319379591836724
                    ],
                    "max": 0.0022319379591836724,
                    "mean": 0.0021912427142857143,
                    "min": 0.002156342204081633,
                    "n": 10,
                    "q_25": 0.0021757791581632647,
                    "q_75": 0.00219842605102041,
                    "std": 2.3349350663489663e-05
                },
                {
                    "ci_99": [
                        0.019335423666666667,
                        0.019564922125353313
                    ],
                    "max": 0.01956061133333331,
                    "mean": 0.019475177000000003,
                    "min": 0.019335423666666667,
                    "n": 7,
                    "q_25": 0.019455998166666676,
                    "q_75": 0.019521697166666664,
                    "std": 6.825669087070038e-05
                },
                {
                    "ci_99": [
                        0.1475144244999964,
                        0.23393037450000362
                    ],
                    "max": 0.1915865590000001,
                    "mean": 0.19072239950000003,
                    "min": 0.18985823999999996,
                    "n": 2,
                    "q_25": 0.19029031975,
                    "q_75": 0.19115447925000006,
                    "std": 0.0008641595000000724
                },
                {
                    "ci_99": [
                        3.471903680555555e-05,
                        3.497635972222225e-05
                    ],
                    "max": 3.497635972222225e-05,
                    "mean": 3.484400399305555e-05,
                    "min": 3.471903680555555e-05,
                    "n": 10,
                    "q_25": 3.4806218489583365e-05,
                    "q_75": 3.4882918402777773e-05,
                    "std": 7.376897117830415e-08
                },
                {
                    "ci_99": [
                        0.00012446359357060825,
                        0.00012535364982778414
                    ],
                    "max": 0.00012535364982778414,
                    "mean": 0.00012477591102181396,
                    "min": 0.00012446359357060825,
                    "n": 10,
                    "q_25": 0.0001245645381745121,
                    "q_75": 0.0001249429945464983,
                    "std": 2.834948086976787e-07
                },
                {
                    "ci_99": [
                        0.0012844342530120487,
                        0.0013269452048192772
                    ],
                    "max": 0.0013269452048192772,
                    "mean": 0.0013004227457831326,
                    "min": 0.0012844342530120487,
                    "n": 10,
                    "q_25": 0.0012894540421686746,
                    "q_75": 0.0013093964457831328,
                    "std": 1.3590506167009398e-05
                },
                {
                    "ci_99": [
                        0.013214518250000001,
                        0.01330744787499999
                    ],
                    "max": 0.01330744787499999,
                    "mean": 0.013253907640625003,
                    "min": 0.013214518250000001,
                    "n": 8,
                    "q_25": 0.013219112562499996,
                    "q_75": 0.01329904753125001,
                    "std": 3.897114852399561e-05
                },
                {
                    "ci_99": [
                        0.16795610899999658,
                        0.1734901090000036
                    ],
                    "max": 0.17077844900000017,
                    "mean": 0.1707231090000001,
                    "min": 0.17066776900000002,
                    "n": 2,
                    "q_25": 0.17069543900000006,
                    "q_75": 0.17075077900000013,
                    "std": 5.534000000007033e-05
                },
                {
                    "ci_99": [
                        3.044703386067164e-05,
                        3.076528004440743e-05
                    ],
                    "max": 3.076528004440743e-05,
                    "mean": 3.063364246461283e-05,
                    "min": 3.044703386067164e-05,
                    "n": 10,
                    "q_25": 3.0532886761032474e-05,
                    "q_75": 3.070209297807381e-05,
                    "std": 1.1131870698602663e-07
                },
                {
                    "ci_99": [
                        9.278159545454543e-05,
                        9.312382454545455e-05
                    ],
                    "max": 9.312382454545455e-05,
                    "mean": 9.295356654545454e-05,
                    "min": 9.278159545454543e-05,
                    "n": 10,
                    "q_25": 9.284393363636365e-05,
                    "q_75": 9.304879181818182e-05,
                    "std": 1.1522124467774076e-07
                },
                {
                    "ci_99": [
                        0.0009237017909090918,
                        0.0009831377818181814
                    ],
                    "max": 0.0009831377818181814,
                    "mean": 0.0009494352372727275,
                    "min": 0.0009237017909090918,
                    "n": 10,
                    "q_25": 0.0009378386977272729,
                    "q_75": 0.0009561294295454555,
                    "std": 1.788832601206036e-05
                },
                {
                    "ci_99": [
                        0.00893143970781407,
                        0.009573485666666678
                    ],
                    "max": 0.009573485666666678,
                    "mean": 0.00919928601190476,
                    "min": 0.008947714750000002,
                    "n": 7,
                    "q_25": 0.009076312499999992,
                    "q_75": 0.009298454374999987,
                    "std": 0.00019382213264079563
                },
                {
                    "ci_99": [
                        0.1323146795000092,
                        0.13646012949999076
                    ],
                    "max": 0.1344288589999998,
                    "mean": 0.13438740449999997,
                    "min": 0.13434595000000016,
                    "n": 2,
                    "q_25": 0.13436667725000007,
                    "q_75": 0.13440813174999988,
                    "std": 4.145449999981565e-05
                },
                {
                    "ci_99": [
                        3.11859737592698e-05,
                        3.162190444951515e-05
                    ],
                    "max": 3.162190444951515e-05,
                    "mean": 3.142151283513975e-05,
                    "min": 3.11859737592698e-05,
                    "n": 10,
                    "q_25": 3.129173252994863e-05,
                    "q_75": 3.154121284940102e-05,
                    "std": 1.395233817989985e-07
                },
                {
                    "ci_99": [
                        9.746187000000003e-05,
                        9.792049727272727e-05
                    ],
                    "max": 9.792049727272727e-05,
                    "mean": 9.771657818181819e-05,
                    "min": 9.746187000000003e-05,
                    "n": 10,
                    "q_25": 9.759058636363636e-05,
                    "q_75": 9.78207354545455e-05,
                    "std": 1.528807276747929e-07
                },
                {
                    "ci_99": [
                        0.0010262946730769235,
                        0.0011010991346153858
                    ],
                    "max": 0.0011010991346153858,
                    "mean": 0.0010513157490384616,
                    "min": 0.0010262946730769235,
                    "n": 10,
                    "q_25": 0.0010313324975961531,
                    "q_75": 0.0010751386514423077,
                    "std": 2.7104768024603916e-05
                },
                {
                    "ci_99": [
                        0.00951247027272727,
                        0.009750352363636377
                    ],
                    "max": 0.009750352363636377,
                    "mean": 0.009584104602272728,
                    "min": 0.00951247027272727,
                    "n": 8,
                    "q_25": 0.00953680784090909,
                    "q_75": 0.009608466931818183,
                    "std": 7.258900977597492e-05
                },
                {
                    "ci_99": [
                        0.14370447550000387,
                        0.14740832549999583
                    ],
                    "max": 0.14559343899999977,
                    "mean": 0.14555640049999985,
                    "min": 0.14551936199999993,
                    "n": 2,
                    "q_25": 0.1455378812499999,
                    "q_75": 0.1455749197499998,
                    "std": 3.7038499999919594e-05
                },
                {
                    "ci_99": [
                        2.579598038728893e-05,
                        2.6149114200595825e-05
                    ],
                    "max": 2.6149114200595825e-05,
                    "mean": 2.59755801142006e-05,
                    "min": 2.579598038728893e-05,
                    "n": 10,
                    "q_25": 2.5907787922045684e-05,
                    "q_75": 2.6053179059086422e-05,
                    "std": 1.1708697748478068e-07
                },
                {
                    "ci_99": [
                        8.127475851851843e-05,
                        8.193120592592597e-05
                    ],
                    "max": 8.193120592592597e-05,
                    "mean": 8.159215585185182e-05,
                    "min": 8.127475851851843e-05,
                    "n": 10,
                    "q_25": 8.14001268518519e-05,
                    "q_75": 8.176705407407405e-05,
                    "std": 2.2688833423694554e-07
                },
                {
                    "ci_99": [
                        0.0007020471578947377,
                        0.0007202638289473686
                    ],
                    "max": 0.0007202638289473686,
                    "mean": 0.0007120008717105265,
                    "min": 0.0007020471578947377,
                    "n": 10,
                    "q_25": 0.0007075840394736838,
                    "q_75": 0.000716372192434211,
                    "std": 6.042152401378467e-06
                },
                {
                    "ci_99": [
                        0.006612747000000002,
                        0.006635312125000001
                    ],
                    "max": 0.006635312125000001,
                    "mean": 0.0066175266484375,
                    "min": 0.006612747000000002,
                    "n": 8,
                    "q_25": 0.0066147077968749975,
                    "q_75": 0.006616454250000001,
                    "std": 6.820789581032928e-06
                },
                {
                    "ci_99": [
                        0.06265916100000302,
                        0.06759576099999698
                    ],
                    "max": 0.06517682699999994,
                    "mean": 0.065127461,
                    "min": 0.06507809500000006,
                    "n": 2,
                    "q_25": 0.06510277800000003,
                    "q_75": 0.06515214399999997,
                    "std": 4.9365999999939625e-05
                }
            ]
        },
        "benchmarks.Histogram1D.time_histogram1d_weights": {
            "params": [
                [
                    "False",
                    "True"
                ],
                [
                    "'>i4'",
                    "'<f4'",
                    "'>f8'",
                    "'<f8'"
                ],
                [
                    "1000.0",
                    "10000.0",
                    "100000.0",
                    "1000000.0",
                    "10000000.0"
                ]
            ],
            "result": [
                0.00031260182011331474,
                0.0007167941546762596,
                0.004811362249999996,
                0.04580346933333339,
                0.4663634980000002,
                0.00026752081851851863,
                0.000479234297777777,
                0.002837682934210527,
                0.02553047950000001,
                0.2523436629999998,
                0.00028444533157894717,
                0.0005648364896907213,
                0.0034968789500000007,
                0.03198809175,
                0.31582132549999997,
                0.00026406188713592234,
                0.0005133847668161438,
                0.003078826382352939,
                0.028270463874999985,
                0.27923771200000025,
                null,
                null,
                null,
                null,
                null,
                null,
                null,
                null,
                null,
                null,
                null,
                null,
                null,
                null,
                null,
                null,
                null,
                null,
                null,
                null
            ],
            "stats": [
                {
                    "ci_99": [
                        0.000311376419263456,
                        0.00031847616713881054
                    ],
                    "max": 0.00031847616713881054,
                    "mean": 0.00031312222124645897,
                    "min": 0.000311376419263456,
                    "n": 10,
                    "q_25": 0.0003119612060906515,
                    "q_75": 0.0003132182145892351,
                    "std": 1.94790937494034e-06
                },
                {
                    "ci_99": [
                        0.0007091007841726625,
                        0.0007199131582733809
                    ],
                    "max": 0.0007199131582733809,
                    "mean": 0.0007156037525179862,
                    "min": 0.0007091007841726625,
                    "n": 10,
                    "q_25": 0.0007120714478417273,
                    "q_75": 0.0007190592877697852,
                    "std": 4.1015021816149635e-06
                },
                {
                    "ci_99": [
                        0.004803499136363637,
                        0.004878095454545458
                    ],
                    "max": 0.004878095454545458,
                    "mean": 0.004823228768181818,
                    "min": 0.004803499136363637,
                    "n": 10,
                    "q_25": 0.004808777738636368,
                    "q_75": 0.004835950784090909,
                    "std": 2.3170969610134672e-05
                },
                {
                    "ci_99": [
                        0.04570966109423491,
                        0.04592953157243174
                    ],
                    "max": 0.04592263099999997,
                    "mean": 0.04581959633333332,
                    "min": 0.045734600333333285,
                    "n": 6,
                    "q_25": 0.04577085458333332,
                    "q_75": 0.045870936083333314,
                    "std": 6.70721927453295e-05
                },
                null,
                {
                    "ci_99": [
                        0.00026723555555555517,
                        0.00026922043456790106
                    ],
                    "max": 0.00026922043456790106,
                    "mean": 0.00026776504049382725,
                    "min": 0.00026723555555555517,
                    "n": 10,
                    "q_25": 0.00026747552345679027,
                    "q_75": 0.00026776677098765454,
                    "std": 5.719804768392866e-07
                },
                {
                    "ci_99": [
                        0.00047612298222222314,
                        0.0004826979777777781
                    ],
                    "max": 0.0004826979777777781,
                    "mean": 0.000479584772888889,
                    "min": 0.00047612298222222314,
                    "n": 10,
                    "q_25": 0.0004775172977777776,
                    "q_75": 0.0004818294466666669,
                    "std": 2.32572185651214e-06
                },
                {
                    "ci_99": [
                        0.002833671157894738,
                        0.0028554691578947375
                    ],
                    "max": 0.0028554691578947375,
                    "mean": 0.00284012622894737,
                    "min": 0.002833671157894738,
                    "n": 10,
                    "q_25": 0.002834732861842105,
                    "q_75": 0.002839649164473687,
                    "std": 7.716413565933046e-06
                },
                {
                    "ci_99": [
                        0.02552154499999998,
                        0.025592422000000004
                    ],
                    "max": 0.025592422000000004,
                    "mean": 0.02554576968749999,
                    "min": 0.02552154499999998,
                    "n": 8,
                    "q_25": 0.025523548125000003,
                    "q_75": 0.025567419874999997,
                    "std": 2.7106695283904186e-05
                },
                {
                    "ci_99": [
                        0.24950456300000368,
                        0.25518276299999587
                    ],
                    "max": 0.2524004449999997,
                    "mean": 0.2523436629999998,
                    "min": 0.25228688099999985,
                    "n": 2,
                    "q_25": 0.2523152719999998,
                    "q_75": 0.25237205399999973,
                    "std": 5.678199999992195e-05
                },
                {
                    "ci_99": [
                        0.0002834442578947368,
                        0.00028537110789473734
                    ],
                    "max": 0.00028537110789473734,
                    "mean": 0.00028436740105263164,
                    "min": 0.0002834442578947368,
                    "n": 10,
                    "q_25": 0.0002843271434210526,
                    "q_75": 0.00028458025986842115,
                    "std": 5.29618875719509e-07
                },
                {
                    "ci_99": [
                        0.0005638810824742271,
                        0.0005714074690721646
                    ],
                    "max": 0.0005714074690721646,
                    "mean": 0.0005670748128865976,
                    "min": 0.0005638810824742271,
                    "n": 10,
                    "q_25": 0.0005642016597938139,
                    "q_75": 0.0005710240399484533,
                    "std": 3.318515465525376e-06
                },
                {
                    "ci_99": [
                        0.003469009766666664,
                        0.0035482078999999962
                    ],
                    "max": 0.0035482078999999962,
                    "mean": 0.003498773286666665,
                    "min": 0.003469009766666664,
                    "n": 10,
                    "q_25": 0.0034887667333333354,
                    "q_75": 0.0035057647416666597,
                    "std": 2.0685736747628335e-05
                },
                {
                    "ci_99": [
                        0.03187538875000001,
                        0.03206480448696625
                    ],
                    "max": 0.0320540835,
                    "mean": 0.03197182092857143,
                    "min": 0.03187538875000001,
                    "n": 7,
                    "q_25": 0.03192067412499998,
                    "q_75": 0.03202191712500002,
                    "std": 6.240464710742927e-05
                },
                {
                    "ci_99": [
                        0.2890503005000058,
                        0.34259235049999415
                    ],
                    "max": 0.31635674599999986,
                    "mean": 0.31582132549999997,
                    "min": 0.3152859050000001,
                    "n": 2,
                    "q_25": 0.31555361525000003,
                    "q_75": 0.3160890357499999,
                    "std": 0.0005354204999998835
                },
                {
                    "ci_99": [
                        0.0002637293543689323,
                        0.0002655269247572816
                    ],
                    "max": 0.0002655269247572816,
                    "mean": 0.0002642253597087379,
                    "min": 0.0002637293543689323,
                    "n": 10,
                    "q_25": 0.00026387973300970855,
                    "q_75": 0.0002641379702669902,
                    "std": 5.383135976563625e-07
                },
                {
                    "ci_99": [
                        0.0004906626726457396,
                        0.0005182021748878919
                    ],
                    "max": 0.0005182021748878919,
                    "mean": 0.0005070283730941704,
                    "min": 0.0004906626726457396,
                    "n": 10,
                    "q_25": 0.0004965481289237667,
                    "q_75": 0.000514628869955157,
                    "std": 1.0272219639670193e-05
                },
                {
                    "ci_99": [
                        0.003070542382352943,
                        0.003139004235294112
                    ],
                    "max": 0.003139004235294112,
                    "mean": 0.0030874475294117632,
                    "min": 0.003070542382352943,
                    "n": 10,
                    "q_25": 0.003073291860294116,
                    "q_75": 0.003090253830882354,
                    "std": 2.0767864515434344e-05
                },
                {
                    "ci_99": [
                        0.028128855499999994,
                        0.028386628499999955
                    ],
                    "max": 0.028386628499999955,
                    "mean": 0.028248708781250007,
                    "min": 0.028128855499999994,
                    "n": 8,
                    "q_25": 0.028178399812500046,
                    "q_75": 0.02828741081250001,
                    "std": 7.941099994178587e-05
                },
                {
                    "ci_99": [
                        0.2566121119999967,
                        0.3018633120000038
                    ],
                    "max": 0.2796902240000003,
                    "mean": 0.27923771200000025,
                    "min": 0.2787852000000002,
                    "n": 2,
                    "q_25": 0.2790114560000002,
                    "q_75": 0.2794639680000003,
                    "std": 0.0004525120000000715
                },
                null,
                null,
                null,
                null,
                null,
                null,
                null,
                null,
                null,
                null,
                null,
                null,
                null,
                null,
                null,
                null,
                null,
                null,
                null,
                null
            ]
        },
        "benchmarks.Histogram2D.time_histogram2d": {
            "params": [
                [
                    "False",
                    "True"
                ],
                [
                    "'>i4'",
                    "'<f4'",
                    "'>f8'",
                    "'<f8'"
                ],
                [
                    "1000.0",
                    "10000.0",
                    "100000.0",
                    "1000000.0",
                    "10000000.0"
                ]
            ],
            "result": [
                0.0008811792258064514,
                0.0017860803333333323,
                0.012888941312499992,
                0.11691836500000008,
                1.3409563140000005,
                0.0009513903136363648,
                0.0020232264433962272,
                0.014543141285714274,
                0.13392055699999994,
                1.583259514,
                0.000955213786363636,
                0.0022467338958333328,
                0.01767407175000002,
                0.15780008899999998,
                1.7777782210000002,
                0.0009648692590909099,
                0.0022251413125000006,
                0.017640573500000017,
                0.15686323600000018,
                1.7881161159999999,
                5.7569134203655313e-05,
                0.00016803091794478518,
                0.0019465885192307675,
                0.01696615357142858,
                0.26197840699999997,
                5.1646304155844174e-05,
                0.00013878037642585557,
                0.0014975386597222231,
                0.013132810625000046,
                0.22158866899999996,
                5.311461866859623e-05,
                0.00015218189778129943,
                0.0016386215895522398,
                0.014295786125000015,
                0.2420962040000001,
                4.419353373493974e-05,
                0.00011132833408071746,
                0.0009928166181818183,
                0.008453514833333323,
                0.0847191304999999
            ],
            "stats": [
                {
                    "ci_99": [
                        0.0008787479032258065,
                        0.0009148725564516126
                    ],
                    "max": 0.0009148725564516126,
                    "mean": 0.0008852214016129031,
                    "min": 0.0008787479032258065,
                    "n": 10,
                    "q_25": 0.0008809161108870978,
                    "q_75": 0.0008837903850806454,
                    "std": 1.0211732023291302e-05
                },
                {
                    "ci_99": [
                        0.0017809815500000011,
                        0.0018134352833333348
                    ],
                    "max": 0.0018134352833333348,
                    "mean": 0.0017917147,
                    "min": 0.0017809815500000011,
                    "n": 10,
                    "q_25": 0.0017827511083333336,
                    "q_75": 0.0018018790000000006,
                    "std": 1.1528064788634168e-05
                },
                {
                    "ci_99": [
                        0.01281231075,
                        0.013853611125000012
                    ],
                    "max": 0.013853611125000012,
                    "mean": 0.0130597792125,
                    "min": 0.01281231075,
                    "n": 10,
                    "q_25": 0.012843901968750009,
                    "q_75": 0.012941519968749999,
                    "std": 0.00038231100335851017
                },
                {
                    "ci_99": [
                        0.11210090137099679,
                        0.11847639834328888
                    ],
                    "max": 0.11734795600000014,
                    "mean": 0.11528864985714284,
                    "min": 0.11282011299999994,
                    "n": 7,
                    "q_25": 0.1128965354999999,
                    "q_75": 0.11707052199999995,
                    "std": 0.0020980855316304315
                },
                null,
                {
                    "ci_99": [
                        0.0009494189000000007,
                        0.0009581496727272729
                    ],
                    "max": 0.0009581496727272729,
                    "mean": 0.0009522573700000002,
                    "min": 0.0009494189000000007,
                    "n": 10,
                    "q_25": 0.0009501709545454545,
                    "q_75": 0.0009542621636363632,
                    "std": 2.736804284100458e-06
                },
                {
                    "ci_99": [
                        0.0020010382452830193,
                        0.002027195735849058
                    ],
                    "max": 0.002027195735849058,
                    "mean": 0.0020189294169811324,
                    "min": 0.0020010382452830193,
                    "n": 10,
                    "q_25": 0.0020179507877358493,
                    "q_75": 0.0020248930471698117,
                    "std": 8.909824820770638e-06
                },
                {
                    "ci_99": [
                        0.014459908142857136,
                        0.015446807000000007
                    ],
                    "max": 0.015446807000000007,
                    "mean": 0.014721805514285716,
                    "min": 0.014459908142857136,
                    "n": 10,
                    "q_25": 0.0144951852857143,
                    "q_75": 0.01470582010714288,
                    "std": 0.00036564010077786834
                },
                {
                    "ci_99": [
                        0.12945202858212124,
                        0.13524404227502138
                    ],
                    "max": 0.13411805600000004,
                    "mean": 0.1323480354285713,
                    "min": 0.12992725900000002,
                    "n": 7,
                    "q_25": 0.13025639649999987,
                    "q_75": 0.1339787914999997,
                    "std": 0.0019105198251657901
                },
                null,
                {
                    "ci_99": [
                        0.0009515779272727257,
                        0.0009587542090909082
                    ],
                    "max": 0.0009587542090909082,
                    "mean": 0.0009552297999999996,
                    "min": 0.0009515779272727257,
                    "n": 10,
                    "q_25": 0.0009539989249999997,
                    "q_75": 0.0009559730431818179,
                    "std": 2.1385729881945753e-06
                },
                {
                    "ci_99": [
                        0.002240403958333336,
                        0.0022538416250000005
                    ],
                    "max": 0.0022538416250000005,
                    "mean": 0.002247879897916667,
                    "min": 0.002240403958333336,
                    "n": 10,
                    "q_25": 0.0022449772708333336,
                    "q_75": 0.0022515857968750017,
                    "std": 4.138514624632531e-06
                },
                {
                    "ci_99": [
                        0.017556470833333337,
                        0.018160045333333336
                    ],
                    "max": 0.018160045333333336,
                    "mean": 0.017742118533333337,
                    "min": 0.017556470833333337,
                    "n": 10,
                    "q_25": 0.017576439999999985,
                    "q_75": 0.01780914225000001,
                    "std": 0.0002032638589740959
                },
                {
                    "ci_99": [
                        0.15060089499999996,
                        0.16293108099999998
                    ],
                    "max": 0.16293108099999998,
                    "mean": 0.15751757833333327,
                    "min": 0.15060089499999996,
                    "n": 6,
                    "q_25": 0.15732801024999987,
                    "q_75": 0.15855202124999995,
                    "std": 0.0036287626430051806
                },
                null,
                {
                    "ci_99": [
                        0.0009529111545454539,
                        0.0010070767818181805
                    ],
                    "max": 0.0010070767818181805,
                    "mean": 0.0009755718936363634,
                    "min": 0.0009529111545454539,
                    "n": 10,
                    "q_25": 0.0009568307704545455,
                    "q_75": 0.0009941781545454538,
                    "std": 2.1080624844519907e-05
                },
                {
                    "ci_99": [
                        0.002220156895833334,
                        0.002233335395833332
                    ],
                    "max": 0.002233335395833332,
                    "mean": 0.0022251446375000004,
                    "min": 0.002220156895833334,
                    "n": 10,
                    "q_25": 0.0022225355937499983,
                    "q_75": 0.0022268775677083373,
                    "std": 3.7258137473298537e-06
                },
                {
                    "ci_99": [
                        0.01759940566666666,
                        0.01822238199999998
                    ],
                    "max": 0.01822238199999998,
                    "mean": 0.017749148816666664,
                    "min": 0.01759940566666666,
                    "n": 10,
                    "q_25": 0.017620854708333328,
                    "q_75": 0.017663337291666678,
                    "std": 0.0002331053065314548
                },
                {
                    "ci_99": [
                        0.14980381899999984,
                        0.15890990282890513
                    ],
                    "max": 0.157550976,
                    "mean": 0.15578849050000004,
                    "min": 0.14980381899999984,
                    "n": 6,
                    "q_25": 0.15653504275000008,
                    "q_75": 0.15713383225000005,
                    "std": 0.00269779274294006
                },
                null,
                {
                    "ci_99": [
                        5.710771697127935e-05,
                        6.035328668407302e-05
                    ],
                    "max": 6.035328668407302e-05,
                    "mean": 5.798849712793735e-05,
                    "min": 5.710771697127935e-05,
                    "n": 10,
                    "q_25": 5.7261681984334246e-05,
                    "q_75": 5.797071736292432e-05,
                    "std": 1.0428188661467398e-06
                },
                {
                    "ci_99": [
                        0.00016748411503067495,
                        0.00016843072392638025
                    ],
                    "max": 0.00016843072392638025,
                    "mean": 0.00016799003619631902,
                    "min": 0.00016748411503067495,
                    "n": 10,
                    "q_25": 0.00016782982438650338,
                    "q_75": 0.00016819264187116565,
                    "std": 2.9369112545383706e-07
                },
                {
                    "ci_99": [
                        0.0018123757115384614,
                        0.001968313519230769
                    ],
                    "max": 0.001968313519230769,
                    "mean": 0.0019242495096153845,
                    "min": 0.0018123757115384614,
                    "n": 10,
                    "q_25": 0.001941554456730771,
                    "q_75": 0.0019539955769230753,
                    "std": 5.356082615235036e-05
                },
                {
                    "ci_99": [
                        0.016089817285714268,
                        0.017531220285714282
                    ],
                    "max": 0.017531220285714282,
                    "mean": 0.016900060238095233,
                    "min": 0.016089817285714268,
                    "n": 6,
                    "q_25": 0.016844255000000006,
                    "q_75": 0.017024084321428552,
                    "std": 0.00042641137604382213
                },
                null,
                {
                    "ci_99": [
                        5.14289137662337e-05,
                        5.188019480519483e-05
                    ],
                    "max": 5.188019480519483e-05,
                    "mean": 5.1662508415584394e-05,
                    "min": 5.14289137662337e-05,
                    "n": 10,
                    "q_25": 5.157313857142854e-05,
                    "q_75": 5.179465415584408e-05,
                    "std": 1.4530744699413273e-07
                },
                {
                    "ci_99": [
                        0.000138569908745247,
                        0.00013894393155893534
                    ],
                    "max": 0.00013894393155893534,
                    "mean": 0.00013875515044359948,
                    "min": 0.000138569908745247,
                    "n": 10,
                    "q_25": 0.000138670696451204,
                    "q_75": 0.00013882920849176176,
                    "std": 1.1133763148221219e-07
                },
                {
                    "ci_99": [
                        0.0014873478888888885,
                        0.001517377722222219
                    ],
                    "max": 0.001517377722222219,
                    "mean": 0.0014978889069444446,
                    "min": 0.0014873478888888885,
                    "n": 10,
                    "q_25": 0.0014943346145833343,
                    "q_75": 0.0015004843819444445,
                    "std": 7.885168389676487e-06
                },
                {
                    "ci_99": [
                        0.013000149159945915,
                        0.013588618375
                    ],
                    "max": 0.013588618375,
                    "mean": 0.013214624517857154,
                    "min": 0.013064325500000001,
                    "n": 7,
                    "q_25": 0.013108542687500016,
                    "q_75": 0.013249765875,
                    "std": 0.00017632601734711705
                },
                null,
                {
                    "ci_99": [
                        5.2484420646406184e-05,
                        5.4059970091654554e-05
                    ],
                    "max": 5.4059970091654554e-05,
                    "mean": 5.311418027013989e-05,
                    "min": 5.2484420646406184e-05,
                    "n": 10,
                    "q_25": 5.294634961408591e-05,
                    "q_75": 5.3286507356488207e-05,
                    "std": 4.2683647123168616e-07
                },
                {
                    "ci_99": [
                        0.00014620705863708372,
                        0.00015734711410459595
                    ],
                    "max": 0.00015734711410459595,
                    "mean": 0.00015217696798732166,
                    "min": 0.00014620705863708372,
                    "n": 10,
                    "q_25": 0.00015042934350237717,
                    "q_75": 0.00015527030625990496,
                    "std": 3.77236655897491e-06
                },
                {
                    "ci_99": [
                        0.001616357552238807,
                        0.001642709134328357
                    ],
                    "max": 0.001642709134328357,
                    "mean": 0.0016331261194029848,
                    "min": 0.001616357552238807,
                    "n": 10,
                    "q_25": 0.0016254540858208935,
                    "q_75": 0.0016395220373134332,
                    "std": 1.0029529804802074e-05
                },
                {
                    "ci_99": [
                        0.014069018749999995,
                        0.014383806407000793
                    ],
                    "max": 0.014335444375000006,
                    "mean": 0.014266252125000004,
                    "min": 0.014069018749999995,
                    "n": 6,
                    "q_25": 0.014274155843750004,
                    "q_75": 0.014324845249999996,
                    "std": 9.120074175157228e-05
                },
                null,
                {
                    "ci_99": [
                        4.39980582329318e-05,
                        4.5113614859437765e-05
                    ],
                    "max": 4.5113614859437765e-05,
                    "mean": 4.428475771084337e-05,
                    "min": 4.39980582329318e-05,
                    "n": 10,
                    "q_25": 4.4079048293172686e-05,
                    "q_75": 4.436126716867469e-05,
                    "std": 3.1100006766382533e-07
                },
                {
                    "ci_99": [
                        0.0001109502511210764,
                        0.00011222875224215231
                    ],
                    "max": 0.00011222875224215231,
                    "mean": 0.00011139027006726462,
                    "min": 0.0001109502511210764,
                    "n": 10,
                    "q_25": 0.00011111925560538112,
                    "q_75": 0.0001114058427690584,
                    "std": 3.935615071245869e-07
                },
                {
                    "ci_99": [
                        0.0009883170909090904,
                        0.001030288909090909
                    ],
                    "max": 0.001030288909090909,
                    "mean": 0.0010014156663636362,
                    "min": 0.0009883170909090904,
                    "n": 10,
                    "q_25": 0.0009901108613636367,
                    "q_75": 0.001011075295454545,
                    "std": 1.5496211328576473e-05
                },
                {
                    "ci_99": [
                        0.008392500916666656,
                        0.008479438339995184
                    ],
                    "max": 0.008465417083333334,
                    "mean": 0.008439790369047614,
                    "min": 0.008392500916666656,
                    "n": 7,
                    "q_25": 0.008419317250000002,
                    "q_75": 0.008464232624999993,
                    "std": 2.7064939401469906e-05
                },
                null
            ]
        },
        "benchmarks.Histogram2D.time_histogram2d_weights": {
            "params": [
                [
                    "False",
                    "True"
                ],
                [
                    "'>i4'",
                    "'<f4'",
                    "'>f8'",
                    "'<f8'"
                ],
                [
                    "1000.0",
                    "10000.0",
                    "100000.0",
                    "1000000.0",
                    "10000000.0"
                ]
            ],
            "result": [
                0.0009001944308943098,
                0.0018268259210526324,
                0.013559970000000008,
                0.12141767100000012,
                1.4495834559999998,
                0.0009306840818181813,
                0.002044892980769232,
                0.0153881575,
                0.1355517704999999,
                1.629868288,
                0.0009422116772727277,
                0.0022827436382978714,
                0.018820887416666654,
                0.16126112700000006,
                1.8666100379999997,
                0.0009264693227272726,
                0.0022480178958333317,
                0.017850944083333313,
                0.15798069950000015,
                1.7944727609999997,
                null,
                null,
                null,
                null,
                null,
                null,
                null,
                null,
                null,
                null,
                null,
                null,
                null,
                null,
                null,
                null,
                null,
                null,
                null,
                null
            ],
            "stats": [
                {
                    "ci_99": [
                        0.000890573764227643,
                        0.0009910386422764214
                    ],
                    "max": 0.0009910386422764214,
                    "mean": 0.0009085517845528456,
                    "min": 0.000890573764227643,
                    "n": 10,
                    "q_25": 0.0008955437886178869,
                    "q_75": 0.0009030439430894317,
                    "std": 2.824721187160886e-05
                },
                {
                    "ci_99": [
                        0.0018127834561403517,
                        0.0018768581228070197
                    ],
                    "max": 0.0018768581228070197,
                    "mean": 0.0018364709385964909,
                    "min": 0.0018127834561403517,
                    "n": 10,
                    "q_25": 0.0018171550833333307,
                    "q_75": 0.0018484941710526317,
                    "std": 2.2934415566641206e-05
                },
                {
                    "ci_99": [
                        0.013441515285714292,
                        0.014280611857142831
                    ],
                    "max": 0.014280611857142831,
                    "mean": 0.013717306757142856,
                    "min": 0.013441515285714292,
                    "n": 10,
                    "q_25": 0.013498671214285718,
                    "q_75": 0.013863314500000005,
                    "std": 0.00031004305082047015
                },
                {
                    "ci_99": [
                        0.11785147753411963,
                        0.12307058646588032
                    ],
                    "max": 0.1224180800000001,
                    "mean": 0.12046103199999998,
                    "min": 0.11839834799999993,
                    "n": 7,
                    "q_25": 0.11858877599999984,
                    "q_75": 0.1219077865,
                    "std": 0.0017084180901221439
                },
                null,
                {
                    "ci_99": [
                        0.0009302225818181813,
                        0.000933624918181818
                    ],
                    "max": 0.000933624918181818,
                    "mean": 0.0009310096309090909,
                    "min": 0.0009302225818181813,
                    "n": 10,
                    "q_25": 0.0009306202522727274,
                    "q_75": 0.0009309595659090907,
                    "std": 9.03000117900812e-07
                },
                {
                    "ci_99": [
                        0.0020258487499999946,
                        0.0020914401538461537
                    ],
                    "max": 0.0020914401538461537,
                    "mean": 0.0020520120519230763,
                    "min": 0.0020258487499999946,
                    "n": 10,
                    "q_25": 0.0020407675096153844,
                    "q_75": 0.002060579350961538,
                    "std": 2.1492290145622985e-05
                },
                {
                    "ci_99": [
                        0.01480438800000002,
                        0.016429402500000006
                    ],
                    "max": 0.016429402500000006,
                    "mean": 0.015409880783333333,
                    "min": 0.01480438800000002,
                    "n": 10,
                    "q_25": 0.01500138600000001,
                    "q_75": 0.015468076041666667,
                    "std": 0.000500161547744078
                },
                {
                    "ci_99": [
                        0.13200489495357443,
                        0.1390327840464256
                    ],
                    "max": 0.1377953540000001,
                    "mean": 0.13551883950000002,
                    "min": 0.13333230400000007,
                    "n": 6,
                    "q_25": 0.13350636625000012,
                    "q_75": 0.13743089749999998,
                    "std": 0.002004280378401203
                },
                null,
                {
                    "ci_99": [
                        0.0009403412545454555,
                        0.0009458229363636353
                    ],
                    "max": 0.0009458229363636353,
                    "mean": 0.0009423513118181822,
                    "min": 0.0009403412545454555,
                    "n": 10,
                    "q_25": 0.0009415829636363651,
                    "q_75": 0.0009427437568181831,
                    "std": 1.472061573440179e-06
                },
                {
                    "ci_99": [
                        0.0022733080638297864,
                        0.0023095053829787267
                    ],
                    "max": 0.0023095053829787267,
                    "mean": 0.002287369795744682,
                    "min": 0.0022733080638297864,
                    "n": 10,
                    "q_25": 0.0022754102021276604,
                    "q_75": 0.002298487702127664,
                    "std": 1.3688419161255349e-05
                },
                {
                    "ci_99": [
                        0.018085661166666673,
                        0.019295385333333342
                    ],
                    "max": 0.019295385333333342,
                    "mean": 0.018740654483333334,
                    "min": 0.018085661166666673,
                    "n": 10,
                    "q_25": 0.018684732541666676,
                    "q_75": 0.018874253375,
                    "std": 0.0003119747503931492
                },
                {
                    "ci_99": [
                        0.15450438600000005,
                        0.1644167794490029
                    ],
                    "max": 0.16297605699999984,
                    "mean": 0.1605145771666667,
                    "min": 0.15450438600000005,
                    "n": 6,
                    "q_25": 0.1605094410000002,
                    "q_75": 0.16243469700000002,
                    "std": 0.0028462049217151016
                },
                null,
                {
                    "ci_99": [
                        0.0009259179272727276,
                        0.0009283276090909085
                    ],
                    "max": 0.0009283276090909085,
                    "mean": 0.000926708905454545,
                    "min": 0.0009259179272727276,
                    "n": 10,
                    "q_25": 0.0009261101568181819,
                    "q_75": 0.0009266581522727271,
                    "std": 8.415256108827236e-07
                },
                {
                    "ci_99": [
                        0.002242346520833332,
                        0.0022862823333333337
                    ],
                    "max": 0.0022862823333333337,
                    "mean": 0.0022564635791666667,
                    "min": 0.002242346520833332,
                    "n": 10,
                    "q_25": 0.0022461200625000003,
                    "q_75": 0.002265951692708335,
                    "std": 1.5856640952432804e-05
                },
                {
                    "ci_99": [
                        0.017695597166666688,
                        0.018396388833333315
                    ],
                    "max": 0.018396388833333315,
                    "mean": 0.017943218066666666,
                    "min": 0.017695597166666688,
                    "n": 10,
                    "q_25": 0.01778163283333334,
                    "q_75": 0.018020461124999998,
                    "std": 0.000224183998471905
                },
                {
                    "ci_99": [
                        0.15076789299999993,
                        0.16611009500000007
                    ],
                    "max": 0.16611009500000007,
                    "mean": 0.15864785666666673,
                    "min": 0.15076789299999993,
                    "n": 6,
                    "q_25": 0.15750941424999998,
                    "q_75": 0.1607667502500001,
                    "std": 0.004644514302256212
                },
                null,
                null,
                null,
                null,
                null,
                null,
                null,
                null,
                null,
                null,
                null,
                null,
                null,
                null,
                null,
                null,
                null,
                null,
                null,
                null,
                null
            ]
        }
    },
    "started_at": {
        "benchmarks.Histogram1D.time_histogram1d": 1532044826000,
        "benchmarks.Histogram1D.time_histogram1d_weights": 1532044918000,
        "benchmarks.Histogram2D.time_histogram2d": 1532044981000,
        "benchmarks.Histogram2D.time_histogram2d_weights": 1532045076000
    },
    "version": 1
}