{
    "benchmark_version": {
        "benchmarks.Histogram1D.time_histogram1d": "e671e48b4a56eddab60af10f82912a1cba894468a35436c61fadd8f0a42c42ce",
        "benchmarks.Histogram1D.time_histogram1d_weights": "4ce26c3fa2d76232a71eb27de69cdc29c1877457e62f92774b7fd8b6376c6685",
        "benchmarks.Histogram2D.time_histogram2d": "c74f482a09eda4dfdbb5380538077d3477a6a3ecfcbadbe3013737a0fb2602af",
        "benchmarks.Histogram2D.time_histogram2d_weights": "321f640418ab3bae617c5a0d2b53a623adb06091393c79f6adffb711140c0af6"
    },
    "commit_hash": "e6aa8c644d631751bcc0eeeeb05e06d8cd9507bf",
    "date": 1537894181000,
    "ended_at": {
        "benchmarks.Histogram1D.time_histogram1d": 1539648663000,
        "benchmarks.Histogram1D.time_histogram1d_weights": 1539648779000,
        "benchmarks.Histogram2D.time_histogram2d": 1539648908000,
        "benchmarks.Histogram2D.time_histogram2d_weights": 1539649038000
    },
    "env_name": "conda-py3.6-cython-nomkl-numpy1.14",
    "params": {
        "arch": "x86_64",
        "cpu": "Intel(R) Celeron(R) CPU N3450 @ 1.10GHz",
        "cython": "",
        "machine": "oneesk",
        "nomkl": "",
        "numpy": "1.14",
        "os": "Ubuntu 16.04.3 LTS",
        "python": "3.6",
        "ram": "3885480"
    },
    "profiles": {},
    "python": "3.6",
    "requirements": {
        "cython": "",
        "nomkl": "",
        "numpy": "1.14"
    },
    "results": {
        "benchmarks.Histogram1D.time_histogram1d": {
            "params": [
                [
                    "False",
                    "True"
                ],
                [
                    "'>i4'",
                    "'<f4'",
                    "'>f8'",
                    "'<f8'"
                ],
                [
                    "1000.0",
                    "10000.0",
                    "100000.0",
                    "1000000.0",
                    "10000000.0"
                ]
            ],
            "result": [
                0.00029523259178743956,
                0.0005988771800000004,
                0.0038548463461538485,
                0.03547121049999996,
                0.3616069890000002,
                0.00026452696212121186,
                0.0004088315282258065,
                0.0020246148846153845,
                0.017905189333333328,
                0.17532934000000022,
                0.00027259694615384603,
                0.0004608363815789473,
                0.0025749389090909125,
                0.022870716000000013,
                0.22948827799999982,
                0.0002629381078431373,
                0.00041440226060606057,
                0.002262609217391305,
                0.019885645000000007,
                0.19593439000000012,
                3.074328599114063e-05,
                0.00011124605073995758,
                0.000916965915254239,
                0.009220973999999993,
                0.09183966099999985,
                2.8336424706482874e-05,
                9.289142033898315e-05,
                0.0007426011081081077,
                0.007511241624999998,
                0.07441081099999991,
                2.8825840929138508e-05,
                9.87425495e-05,
                0.0009096975318181816,
                0.008514778111111109,
                0.08343299399999982,
                2.5368627076784892e-05,
                8.405578253968261e-05,
                0.0007368531164383567,
                0.006881354250000004,
                0.06738430099999992
            ],
            "stats": [
                {
                    "ci_99": [
                        0.0002940745507246385,
                        0.000297828850241546
                    ],
                    "max": 0.000297828850241546,
                    "mean": 0.00029566584685990335,
                    "min": 0.0002940745507246385,
                    "n": 10,
                    "q_25": 0.0002947560748792267,
                    "q_75": 0.00029669604468599047,
                    "std": 1.2007681648345963e-06
                },
                {
                    "ci_99": [
                        0.0005916911999999996,
                        0.0006029392499999986
                    ],
                    "max": 0.0006029392499999986,
                    "mean": 0.0005980332729999999,
                    "min": 0.0005916911999999996,
                    "n": 10,
                    "q_25": 0.0005945155124999998,
                    "q_75": 0.0006013547524999999,
                    "std": 3.7406202582781112e-06
                },
                {
                    "ci_99": [
                        0.0038396985384615387,
                        0.003863946559567902
                    ],
                    "max": 0.0038599320000000017,
                    "mean": 0.0038523175705128215,
                    "min": 0.0038396985384615387,
                    "n": 6,
                    "q_25": 0.003847795798076924,
                    "q_75": 0.0038580640192307706,
                    "std": 7.289768729182504e-06
                },
                {
                    "ci_99": [
                        0.0352780412721614,
                        0.03586141549999999
                    ],
                    "max": 0.03586141549999999,
                    "mean": 0.035539630499999995,
                    "min": 0.035413660500000055,
                    "n": 5,
                    "q_25": 0.035449381,
                    "q_75": 0.03550248499999997,
                    "std": 0.00016347482004607864
                },
                null,
                {
                    "ci_99": [
                        0.0002618484494949497,
                        0.0002661590656565653
                    ],
                    "max": 0.0002661590656565653,
                    "mean": 0.0002642905166666666,
                    "min": 0.0002618484494949497,
                    "n": 10,
                    "q_25": 0.0002634544469696972,
                    "q_75": 0.00026515810858585866,
                    "std": 1.2049654476086343e-06
                },
                {
                    "ci_99": [
                        0.0004005867741935482,
                        0.00041398820161290335
                    ],
                    "max": 0.00041398820161290335,
                    "mean": 0.0004076155588709678,
                    "min": 0.0004005867741935482,
                    "n": 10,
                    "q_25": 0.00040461379435483827,
                    "q_75": 0.0004095365645161296,
                    "std": 4.356211582773578e-06
                },
                {
                    "ci_99": [
                        0.002000727076923076,
                        0.0020628097307692304
                    ],
                    "max": 0.0020628097307692304,
                    "mean": 0.0020275893576923074,
                    "min": 0.002000727076923076,
                    "n": 10,
                    "q_25": 0.0020173647403846136,
                    "q_75": 0.002037356615384616,
                    "std": 1.645076484822943e-05
                },
                {
                    "ci_99": [
                        0.017597841999999992,
                        0.018043317152646652
                    ],
                    "max": 0.017975391000000007,
                    "mean": 0.017838742055555547,
                    "min": 0.017597841999999992,
                    "n": 6,
                    "q_25": 0.01776731833333331,
                    "q_75": 0.017921906833333324,
                    "std": 0.00013296761173370476
                },
                null,
                {
                    "ci_99": [
                        0.00027129742051282057,
                        0.0002746799538461541
                    ],
                    "max": 0.0002746799538461541,
                    "mean": 0.0002727447128205128,
                    "min": 0.00027129742051282057,
                    "n": 10,
                    "q_25": 0.0002721394397435894,
                    "q_75": 0.0002730964487179489,
                    "std": 9.37314210294768e-07
                },
                {
                    "ci_99": [
                        0.000453485245614036,
                        0.00047404962280701726
                    ],
                    "max": 0.00047404962280701726,
                    "mean": 0.0004627705921052631,
                    "min": 0.000453485245614036,
                    "n": 10,
                    "q_25": 0.000457949059210526,
                    "q_75": 0.00046860366447368435,
                    "std": 6.566241239027062e-06
                },
                {
                    "ci_99": [
                        0.002550545772727271,
                        0.0026707640909091005
                    ],
                    "max": 0.0026707640909091005,
                    "mean": 0.0025804385136363648,
                    "min": 0.002550545772727271,
                    "n": 10,
                    "q_25": 0.0025601579318181794,
                    "q_75": 0.0025820134659090893,
                    "std": 3.2285554823706855e-05
                },
                {
                    "ci_99": [
                        0.022744661543762982,
                        0.023117100999999973
                    ],
                    "max": 0.023117100999999973,
                    "mean": 0.022911072066666666,
                    "min": 0.022835963666666664,
                    "n": 5,
                    "q_25": 0.0228465246666667,
                    "q_75": 0.02288505499999997,
                    "std": 0.00010446153343936592
                },
                null,
                {
                    "ci_99": [
                        0.0002613400931372549,
                        0.00026382647058823525
                    ],
                    "max": 0.00026382647058823525,
                    "mean": 0.0002626971377450983,
                    "min": 0.0002613400931372549,
                    "n": 10,
                    "q_25": 0.0002620919803921577,
                    "q_75": 0.00026336461397058844,
                    "std": 8.49117058184993e-07
                },
                {
                    "ci_99": [
                        0.0004104207878787874,
                        0.0004164837939393935
                    ],
                    "max": 0.0004164837939393935,
                    "mean": 0.00041382419999999977,
                    "min": 0.0004104207878787874,
                    "n": 9,
                    "q_25": 0.00041215763030303087,
                    "q_75": 0.0004151355696969692,
                    "std": 1.9330293314623328e-06
                },
                {
                    "ci_99": [
                        0.002247230000000001,
                        0.0022752458695652175
                    ],
                    "max": 0.0022752458695652175,
                    "mean": 0.00226179057826087,
                    "min": 0.002247230000000001,
                    "n": 10,
                    "q_25": 0.002253921826086958,
                    "q_75": 0.0022689676739130436,
                    "std": 9.161010285233022e-06
                },
                {
                    "ci_99": [
                        0.019745095684527397,
                        0.020139415333333337
                    ],
                    "max": 0.020139415333333337,
                    "mean": 0.019938428000000005,
                    "min": 0.01981072166666668,
                    "n": 6,
                    "q_25": 0.01985031716666666,
                    "q_75": 0.02002436108333333,
                    "std": 0.00012109936750133012
                },
                null,
                {
                    "ci_99": [
                        3.06053521594684e-05,
                        3.088731007751933e-05
                    ],
                    "max": 3.088731007751933e-05,
                    "mean": 3.07389875968992e-05,
                    "min": 3.06053521594684e-05,
                    "n": 10,
                    "q_25": 3.068375138427465e-05,
                    "q_75": 3.076047314507194e-05,
                    "std": 7.694499150744504e-08
                },
                {
                    "ci_99": [
                        0.00011081598731501054,
                        0.00011183775898520085
                    ],
                    "max": 0.00011183775898520085,
                    "mean": 0.00011122664228329813,
                    "min": 0.00011081598731501054,
                    "n": 10,
                    "q_25": 0.00011109582293868927,
                    "q_75": 0.00011130287790697685,
                    "std": 2.614642716678681e-07
                },
                {
                    "ci_99": [
                        0.0009113313559322019,
                        0.000919144610169492
                    ],
                    "max": 0.000919144610169492,
                    "mean": 0.000916320452542373,
                    "min": 0.0009113313559322019,
                    "n": 10,
                    "q_25": 0.0009144653050847459,
                    "q_75": 0.0009182901228813568,
                    "std": 2.400376935306034e-06
                },
                {
                    "ci_99": [
                        0.009116027880037774,
                        0.00928856799996222
                    ],
                    "max": 0.009261714100000007,
                    "mean": 0.009202297939999996,
                    "min": 0.009152557999999988,
                    "n": 5,
                    "q_25": 0.009154761300000003,
                    "q_75": 0.009221482299999995,
                    "std": 4.2381384424233555e-05
                },
                null,
                {
                    "ci_99": [
                        2.8048074017355816e-05,
                        2.844275140377741e-05
                    ],
                    "max": 2.844275140377741e-05,
                    "mean": 2.8279544665645723e-05,
                    "min": 2.8048074017355816e-05,
                    "n": 10,
                    "q_25": 2.816911089841753e-05,
                    "q_75": 2.835622970903517e-05,
                    "std": 1.3176382398953712e-07
                },
                {
                    "ci_99": [
                        9.262724237288139e-05,
                        9.381033220338985e-05
                    ],
                    "max": 9.381033220338985e-05,
                    "mean": 9.301263627118646e-05,
                    "min": 9.262724237288139e-05,
                    "n": 10,
                    "q_25": 9.27184038135594e-05,
                    "q_75": 9.313722161016953e-05,
                    "std": 3.676758447068723e-07
                },
                {
                    "ci_99": [
                        0.0007400379999999999,
                        0.0007476014594594617
                    ],
                    "max": 0.0007476014594594617,
                    "mean": 0.0007432013135135133,
                    "min": 0.0007400379999999999,
                    "n": 10,
                    "q_25": 0.000741367496621621,
                    "q_75": 0.0007450552499999993,
                    "std": 2.5632955750929155e-06
                },
                {
                    "ci_99": [
                        0.0074920032598118445,
                        0.007541958999999987
                    ],
                    "max": 0.007541958999999987,
                    "mean": 0.007515580225000001,
                    "min": 0.007504278000000003,
                    "n": 5,
                    "q_25": 0.007505502999999997,
                    "q_75": 0.007514919500000022,
                    "std": 1.374329313983222e-05
                },
                null,
                {
                    "ci_99": [
                        2.8688400176418756e-05,
                        2.893716583357838e-05
                    ],
                    "max": 2.893716583357838e-05,
                    "mean": 2.8811327046666955e-05,
                    "min": 2.8688400176418756e-05,
                    "n": 7,
                    "q_25": 2.8762194501617178e-05,
                    "q_75": 2.8851746692149333e-05,
                    "std": 8.002003778218695e-08
                },
                {
                    "ci_99": [
                        9.842932675750211e-05,
                        9.900290490916454e-05
                    ],
                    "max": 9.8940959e-05,
                    "mean": 9.871611583333333e-05,
                    "min": 9.843583299999991e-05,
                    "n": 6,
                    "q_25": 9.860021375000002e-05,
                    "q_75": 9.884716399999999e-05,
                    "std": 1.7303791751466247e-07
                },
                {
                    "ci_99": [
                        0.0008940526717666127,
                        0.0009226732767182357
                    ],
                    "max": 0.0009195414272727268,
                    "mean": 0.0009083629742424243,
                    "min": 0.0008969007545454548,
                    "n": 6,
                    "q_25": 0.0009010198568181814,
                    "q_75": 0.0009145843590909096,
                    "std": 8.359484560132054e-06
                },
                {
                    "ci_99": [
                        0.008476053444444452,
                        0.008544602919692895
                    ],
                    "max": 0.008530367888888883,
                    "mean": 0.008511764955555558,
                    "min": 0.008476053444444452,
                    "n": 5,
                    "q_25": 0.008513762888888894,
                    "q_75": 0.00852386244444445,
                    "std": 1.8872208327940973e-05
                },
                null,
                {
                    "ci_99": [
                        2.5141978895374968e-05,
                        2.549122766052985e-05
                    ],
                    "max": 2.549122766052985e-05,
                    "mean": 2.5360211270767856e-05,
                    "min": 2.5141978895374968e-05,
                    "n": 10,
                    "q_25": 2.5274221149528556e-05,
                    "q_75": 2.5467535024696942e-05,
                    "std": 1.1241119860015022e-07
                },
                {
                    "ci_99": [
                        8.370563174603173e-05,
                        8.443308888888883e-05
                    ],
                    "max": 8.443308888888883e-05,
                    "mean": 8.40740584126984e-05,
                    "min": 8.370563174603173e-05,
                    "n": 10,
                    "q_25": 8.394967857142846e-05,
                    "q_75": 8.424402738095234e-05,
                    "std": 2.3208822667542596e-07
                },
                {
                    "ci_99": [
                        0.0007236197397260265,
                        0.0007428330821917814
                    ],
                    "max": 0.0007428330821917814,
                    "mean": 0.0007350477164383561,
                    "min": 0.0007236197397260265,
                    "n": 10,
                    "q_25": 0.0007285457876712324,
                    "q_75": 0.0007415825068493165,
                    "std": 7.147959672466066e-06
                },
                {
                    "ci_99": [
                        0.006872698720969624,
                        0.00690212160000001
                    ],
                    "max": 0.00690212160000001,
                    "mean": 0.006884492050000006,
                    "min": 0.006876842700000019,
                    "n": 6,
                    "q_25": 0.006879092824999997,
                    "q_75": 0.006885543925,
                    "std": 8.458413616581982e-06
                },
                null
            ]
        },
        "benchmarks.Histogram1D.time_histogram1d_weights": {
            "params": [
                [
                    "False",
                    "True"
                ],
                [
                    "'>i4'",
                    "'<f4'",
                    "'>f8'",
                    "'<f8'"
                ],
                [
                    "1000.0",
                    "10000.0",
                    "100000.0",
                    "1000000.0",
                    "10000000.0"
                ]
            ],
            "result": [
                0.000328790668789809,
                0.0007690601283783787,
                0.004981673090909093,
                0.04703242100000002,
                0.4800369200000003,
                0.00028421162105263156,
                0.0005056027649999995,
                0.0028960272000000007,
                0.026143860500000005,
                0.25796195300000013,
                0.0002950787872340422,
                0.0005797878469387753,
                0.0035502350000000088,
                0.03285436050000001,
                0.32551459100000013,
                0.0002778061128205129,
                0.0005147141849999998,
                0.0031897027499999983,
                0.028756010499999984,
                0.28553328600000016,
                3.369912933857234e-05,
                0.00013518351406926408,
                0.0012511399374999996,
                0.011696771599999989,
                0.11637072599999998,
                2.9399602356020932e-05,
                9.97314471074379e-05,
                0.0009196677213114752,
                0.008365819714285707,
                0.082599219,
                3.089524589646466e-05,
                0.00011234939953271044,
                0.0011460133695652154,
                0.010324477333333323,
                0.1017493410000001,
                2.602022293538725e-05,
                8.167722861586322e-05,
                0.0008053158142857135,
                0.007047231849999991,
                0.06907496599999985
            ],
            "stats": [
                {
                    "ci_99": [
                        0.0003246391401273887,
                        0.00033143104458598766
                    ],
                    "max": 0.00033143104458598766,
                    "mean": 0.00032839314522292994,
                    "min": 0.0003246391401273887,
                    "n": 10,
                    "q_25": 0.0003278760207006367,
                    "q_75": 0.0003294145063694267,
                    "std": 1.8131083600684855e-06
                },
                {
                    "ci_99": [
                        0.0007382612027027028,
                        0.0008202572432432423
                    ],
                    "max": 0.0008202572432432423,
                    "mean": 0.0007691909999999996,
                    "min": 0.0007382612027027028,
                    "n": 10,
                    "q_25": 0.0007463849763513521,
                    "q_75": 0.0007785282432432414,
                    "std": 2.4779995878783167e-05
                },
                {
                    "ci_99": [
                        0.004932127818181814,
                        0.005015436090909093
                    ],
                    "max": 0.005015436090909093,
                    "mean": 0.0049777013818181805,
                    "min": 0.004932127818181814,
                    "n": 10,
                    "q_25": 0.004955530090909094,
                    "q_75": 0.004996785636363632,
                    "std": 2.6373364349825057e-05
                },
                {
                    "ci_99": [
                        0.04654631154719298,
                        0.04759469520280702
                    ],
                    "max": 0.047368610499999964,
                    "mean": 0.047070503375,
                    "min": 0.04684856100000001,
                    "n": 4,
                    "q_25": 0.04694061262500003,
                    "q_75": 0.04716231174999999,
                    "std": 0.0001926779822450879
                },
                null,
                {
                    "ci_99": [
                        0.0002797826052631575,
                        0.0002858361578947366
                    ],
                    "max": 0.0002858361578947366,
                    "mean": 0.00028405555473684193,
                    "min": 0.0002797826052631575,
                    "n": 10,
                    "q_25": 0.00028342476842105216,
                    "q_75": 0.0002853704026315793,
                    "std": 1.6977390253872491e-06
                },
                {
                    "ci_99": [
                        0.0005026415699999997,
                        0.00052658235
                    ],
                    "max": 0.00052658235,
                    "mean": 0.0005095701269999996,
                    "min": 0.0005026415699999997,
                    "n": 10,
                    "q_25": 0.0005043674599999995,
                    "q_75": 0.0005094435099999994,
                    "std": 8.44889574555433e-06
                },
                {
                    "ci_99": [
                        0.002828625750000002,
                        0.0029095276999999975
                    ],
                    "max": 0.0029095276999999975,
                    "mean": 0.002889229395000001,
                    "min": 0.002828625750000002,
                    "n": 10,
                    "q_25": 0.002885948737499999,
                    "q_75": 0.0029006568249999947,
                    "std": 2.18626538908176e-05
                },
                {
                    "ci_99": [
                        0.02607548160988429,
                        0.02622057324725858
                    ],
                    "max": 0.02621221600000001,
                    "mean": 0.026148027428571436,
                    "min": 0.02607856549999993,
                    "n": 7,
                    "q_25": 0.026112049750000033,
                    "q_75": 0.026188725250000017,
                    "std": 4.989335015199643e-05
                },
                null,
                {
                    "ci_99": [
                        0.000293546159574468,
                        0.0002955779148936167
                    ],
                    "max": 0.0002955779148936167,
                    "mean": 0.0002946786797872339,
                    "min": 0.000293546159574468,
                    "n": 10,
                    "q_25": 0.00029391131382978735,
                    "q_75": 0.0002953517553191488,
                    "std": 7.881484774047757e-07
                },
                {
                    "ci_99": [
                        0.0005764134387755092,
                        0.000586822040816327
                    ],
                    "max": 0.000586822040816327,
                    "mean": 0.0005812616214285712,
                    "min": 0.0005764134387755092,
                    "n": 10,
                    "q_25": 0.0005791151275510201,
                    "q_75": 0.000584958316326531,
                    "std": 3.6530506419202363e-06
                },
                {
                    "ci_99": [
                        0.003512393666666669,
                        0.0035631798666666695
                    ],
                    "max": 0.0035631798666666695,
                    "mean": 0.003544504940740743,
                    "min": 0.003512393666666669,
                    "n": 9,
                    "q_25": 0.003532676133333338,
                    "q_75": 0.003556022733333338,
                    "std": 1.5183308742101941e-05
                },
                {
                    "ci_99": [
                        0.0326027599001521,
                        0.033042739899847906
                    ],
                    "max": 0.03296648150000003,
                    "mean": 0.0328227499,
                    "min": 0.032642030000000044,
                    "n": 5,
                    "q_25": 0.032760497,
                    "q_75": 0.03289038049999993,
                    "std": 0.00011204196244415273
                },
                null,
                {
                    "ci_99": [
                        0.00027507471794871723,
                        0.0002808532923076923
                    ],
                    "max": 0.0002808532923076923,
                    "mean": 0.00027813870256410264,
                    "min": 0.00027507471794871723,
                    "n": 10,
                    "q_25": 0.0002770860666666665,
                    "q_75": 0.0002794112948717953,
                    "std": 1.6131526411227936e-06
                },
                {
                    "ci_99": [
                        0.0005124639200000003,
                        0.0005183559899999989
                    ],
                    "max": 0.0005183559899999989,
                    "mean": 0.0005152104329999999,
                    "min": 0.0005124639200000003,
                    "n": 10,
                    "q_25": 0.0005134433425000001,
                    "q_75": 0.0005173764850000001,
                    "std": 2.1164841306751126e-06
                },
                {
                    "ci_99": [
                        0.003155271277777779,
                        0.0032183397222222223
                    ],
                    "max": 0.0032183397222222223,
                    "mean": 0.0031901250222222213,
                    "min": 0.003155271277777779,
                    "n": 10,
                    "q_25": 0.003183651791666668,
                    "q_75": 0.0032043011527777754,
                    "std": 1.9029689677477783e-05
                },
                {
                    "ci_99": [
                        0.02870045523720769,
                        0.02886094950000001
                    ],
                    "max": 0.02886094950000001,
                    "mean": 0.028771809333333325,
                    "min": 0.028723567499999936,
                    "n": 6,
                    "q_25": 0.028738070375000035,
                    "q_75": 0.028790673374999978,
                    "std": 4.664853619414383e-05
                },
                null,
                {
                    "ci_99": [
                        3.340777013752459e-05,
                        3.423158218729536e-05
                    ],
                    "max": 3.423158218729536e-05,
                    "mean": 3.3703806352324815e-05,
                    "min": 3.340777013752459e-05,
                    "n": 10,
                    "q_25": 3.354091666666665e-05,
                    "q_75": 3.3715624754420444e-05,
                    "std": 2.356098446544135e-07
                },
                {
                    "ci_99": [
                        0.00013476290259740268,
                        0.00013613242424242398
                    ],
                    "max": 0.00013613242424242398,
                    "mean": 0.00013519869415584414,
                    "min": 0.00013476290259740268,
                    "n": 10,
                    "q_25": 0.00013495164448051956,
                    "q_75": 0.0001353215281385279,
                    "std": 3.758943938240565e-07
                },
                {
                    "ci_99": [
                        0.0012423173500000022,
                        0.0012648767500000018
                    ],
                    "max": 0.0012648767500000018,
                    "mean": 0.0012519748650000001,
                    "min": 0.0012423173500000022,
                    "n": 10,
                    "q_25": 0.0012473473437499987,
                    "q_75": 0.0012546213374999998,
                    "std": 6.7927950271151815e-06
                },
                {
                    "ci_99": [
                        0.011599263199999998,
                        0.01179088638237805
                    ],
                    "max": 0.011780580600000002,
                    "mean": 0.011697803533333327,
                    "min": 0.011599263199999998,
                    "n": 6,
                    "q_25": 0.011672014199999985,
                    "q_75": 0.011736447250000002,
                    "std": 5.801150193110509e-05
                },
                null,
                {
                    "ci_99": [
                        2.918110418848169e-05,
                        2.958146439790575e-05
                    ],
                    "max": 2.958146439790575e-05,
                    "mean": 2.9404409842931936e-05,
                    "min": 2.918110418848169e-05,
                    "n": 10,
                    "q_25": 2.933447028795814e-05,
                    "q_75": 2.948879175392673e-05,
                    "std": 1.1135192042177236e-07
                },
                {
                    "ci_99": [
                        9.920905289256205e-05,
                        0.00010024913719008272
                    ],
                    "max": 0.00010024913719008272,
                    "mean": 9.974840392561977e-05,
                    "min": 9.920905289256205e-05,
                    "n": 8,
                    "q_25": 9.95207293388429e-05,
                    "q_75": 9.998892148760323e-05,
                    "std": 3.2297117769247995e-07
                },
                {
                    "ci_99": [
                        0.0009023912295081963,
                        0.000923726459016394
                    ],
                    "max": 0.000923726459016394,
                    "mean": 0.0009152586684881599,
                    "min": 0.0009023912295081963,
                    "n": 9,
                    "q_25": 0.0009053853606557383,
                    "q_75": 0.0009210638196721305,
                    "std": 8.319092939907423e-06
                },
                {
                    "ci_99": [
                        0.008322537441469774,
                        0.008455029571428565
                    ],
                    "max": 0.008455029571428565,
                    "mean": 0.008380440571428567,
                    "min": 0.008355476428571438,
                    "n": 5,
                    "q_25": 0.008358774999999994,
                    "q_75": 0.008367102142857139,
                    "std": 3.75441273044521e-05
                },
                null,
                {
                    "ci_99": [
                        3.069680492424246e-05,
                        3.111729166666667e-05
                    ],
                    "max": 3.111729166666667e-05,
                    "mean": 3.089692285353536e-05,
                    "min": 3.069680492424246e-05,
                    "n": 10,
                    "q_25": 3.082643655303026e-05,
                    "q_75": 3.0962922821969705e-05,
                    "std": 1.1899741343976286e-07
                },
                {
                    "ci_99": [
                        0.00011182703271028045,
                        0.00011321319859813105
                    ],
                    "max": 0.00011321319859813105,
                    "mean": 0.0001124657640186917,
                    "min": 0.00011182703271028045,
                    "n": 10,
                    "q_25": 0.00011198572546728983,
                    "q_75": 0.00011296320210280393,
                    "std": 5.159207347174037e-07
                },
                {
                    "ci_99": [
                        0.0011272935000000005,
                        0.0011508624999999992
                    ],
                    "max": 0.0011508624999999992,
                    "mean": 0.0011444750369565214,
                    "min": 0.0011272935000000005,
                    "n": 10,
                    "q_25": 0.0011429044076086963,
                    "q_75": 0.0011490107663043477,
                    "std": 6.564277033367337e-06
                },
                {
                    "ci_99": [
                        0.0102963930783059,
                        0.010358803055027423
                    ],
                    "max": 0.010355866166666653,
                    "mean": 0.010327598066666662,
                    "min": 0.01030616533333332,
                    "n": 5,
                    "q_25": 0.010318888000000007,
                    "q_75": 0.010332593500000006,
                    "std": 1.65469400664346e-05
                },
                null,
                {
                    "ci_99": [
                        2.5803243474540002e-05,
                        2.6116789045785187e-05
                    ],
                    "max": 2.6116789045785187e-05,
                    "mean": 2.6005391228070166e-05,
                    "min": 2.5803243474540002e-05,
                    "n": 10,
                    "q_25": 2.599505006418487e-05,
                    "q_75": 2.6052504172015406e-05,
                    "std": 8.150268246660865e-08
                },
                {
                    "ci_99": [
                        8.132845101088632e-05,
                        8.22603452566097e-05
                    ],
                    "max": 8.22603452566097e-05,
                    "mean": 8.17323458786936e-05,
                    "min": 8.132845101088632e-05,
                    "n": 10,
                    "q_25": 8.140916018662513e-05,
                    "q_75": 8.20466947900466e-05,
                    "std": 3.3120024136776966e-07
                },
                {
                    "ci_99": [
                        0.0008034050142857138,
                        0.0008065077428571432
                    ],
                    "max": 0.0008065077428571432,
                    "mean": 0.000805012806349206,
                    "min": 0.0008034050142857138,
                    "n": 9,
                    "q_25": 0.0008041163714285712,
                    "q_75": 0.0008057572142857136,
                    "std": 9.97598716308986e-07
                },
                {
                    "ci_99": [
                        0.006998081299999992,
                        0.007074014907729775
                    ],
                    "max": 0.007059093799999994,
                    "mean": 0.007036426333333327,
                    "min": 0.006998081299999992,
                    "n": 6,
                    "q_25": 0.007019042600000001,
                    "q_75": 0.0070547627249999915,
                    "std": 2.3601435914129564e-05
                },
                null
            ]
        },
        "benchmarks.Histogram2D.time_histogram2d": {
            "params": [
                [
                    "False",
                    "True"
                ],
                [
                    "'>i4'",
                    "'<f4'",
                    "'>f8'",
                    "'<f8'"
                ],
                [
                    "1000.0",
                    "10000.0",
                    "100000.0",
                    "1000000.0",
                    "10000000.0"
                ]
            ],
            "result": [
                0.0009219382711864411,
                0.001881081448275862,
                0.013157521875000008,
                0.1175013439999999,
                1.3749155070000003,
                0.0009911024900000009,
                0.002091148907407408,
                0.014859307999999988,
                0.13491454400000014,
                1.5818160079999999,
                0.0009965643363636367,
                0.0023154286304347804,
                0.018038393000000007,
                0.159896402,
                1.809410723,
                0.0009863740272727283,
                0.002325780021739127,
                0.017951139999999994,
                0.15868941300000006,
                1.8150669009999998,
                4.917342300000005e-05,
                0.00016328314608433724,
                0.0014353658142857145,
                0.013126212750000033,
                0.13395383600000033,
                4.451336301950806e-05,
                0.00012751700225733625,
                0.0010997726078431364,
                0.009839493999999985,
                0.09694344300000024,
                4.557423284734128e-05,
                0.000139907272845953,
                0.0013320656428571392,
                0.011791316200000023,
                0.11646738000000045,
                4.132637934863065e-05,
                0.00011039069961240305,
                0.0009922898396226413,
                0.008522932499999969,
                0.0847822869999999
            ],
            "stats": [
                {
                    "ci_99": [
                        0.0009147184067796606,
                        0.0009267098813559329
                    ],
                    "max": 0.0009267098813559329,
                    "mean": 0.0009214004525423732,
                    "min": 0.0009147184067796606,
                    "n": 10,
                    "q_25": 0.0009185576694915264,
                    "q_75": 0.0009248237415254246,
                    "std": 4.211395508796946e-06
                },
                {
                    "ci_99": [
                        0.0018625343103448266,
                        0.0019088649999999933
                    ],
                    "max": 0.0019088649999999933,
                    "mean": 0.0018832041103448265,
                    "min": 0.0018625343103448266,
                    "n": 10,
                    "q_25": 0.001874889836206896,
                    "q_75": 0.0018893155775862047,
                    "std": 1.336023370026628e-05
                },
                {
                    "ci_99": [
                        0.012857952000000006,
                        0.013979524249999986
                    ],
                    "max": 0.013979524249999986,
                    "mean": 0.013287446600000002,
                    "min": 0.012857952000000006,
                    "n": 10,
                    "q_25": 0.013067360250000014,
                    "q_75": 0.013305965187500005,
                    "std": 0.00035254302918244496
                },
                {
                    "ci_99": [
                        0.1056872418944459,
                        0.12681024477222064
                    ],
                    "max": 0.117777154,
                    "mean": 0.11624874333333328,
                    "min": 0.11346773199999993,
                    "n": 3,
                    "q_25": 0.11548453799999991,
                    "q_75": 0.11763924899999995,
                    "std": 0.0019696930075727343
                },
                null,
                {
                    "ci_99": [
                        0.0009517804499999993,
                        0.0010029218898732198
                    ],
                    "max": 0.0009983206,
                    "mean": 0.0009846065228571426,
                    "min": 0.0009517804499999993,
                    "n": 7,
                    "q_25": 0.0009811924049999998,
                    "q_75": 0.0009943286549999996,
                    "std": 1.4783773394411646e-05
                },
                {
                    "ci_99": [
                        0.0020747699999999953,
                        0.002108917074074074
                    ],
                    "max": 0.002108917074074074,
                    "mean": 0.0020898892703703703,
                    "min": 0.0020747699999999953,
                    "n": 10,
                    "q_25": 0.00207894589814815,
                    "q_75": 0.0020962101018518506,
                    "std": 1.1340733223357962e-05
                },
                {
                    "ci_99": [
                        0.01460436200000001,
                        0.015908907249999993
                    ],
                    "max": 0.015908907249999993,
                    "mean": 0.015004161875000002,
                    "min": 0.01460436200000001,
                    "n": 10,
                    "q_25": 0.014780675125000017,
                    "q_75": 0.015060588624999989,
                    "std": 0.0003664259477392206
                },
                {
                    "ci_99": [
                        0.12324860951649326,
                        0.1444477758168399
                    ],
                    "max": 0.135529727,
                    "mean": 0.1338481926666667,
                    "min": 0.13110030699999997,
                    "n": 3,
                    "q_25": 0.13300742550000005,
                    "q_75": 0.13522213550000006,
                    "std": 0.001959212300675374
                },
                null,
                {
                    "ci_99": [
                        0.0009917521636363634,
                        0.0010011516363636367
                    ],
                    "max": 0.0010011516363636367,
                    "mean": 0.0009964172072727282,
                    "min": 0.0009917521636363634,
                    "n": 10,
                    "q_25": 0.0009943127681818183,
                    "q_75": 0.0009984458954545472,
                    "std": 2.9811605826899552e-06
                },
                {
                    "ci_99": [
                        0.0023064859565217395,
                        0.0023379163913043515
                    ],
                    "max": 0.0023379163913043515,
                    "mean": 0.0023168656739130434,
                    "min": 0.0023064859565217395,
                    "n": 10,
                    "q_25": 0.002311487260869566,
                    "q_75": 0.002319564869565217,
                    "std": 8.532156453975398e-06
                },
                {
                    "ci_99": [
                        0.01794051166666666,
                        0.018516023666666676
                    ],
                    "max": 0.018516023666666676,
                    "mean": 0.018106051733333343,
                    "min": 0.01794051166666666,
                    "n": 10,
                    "q_25": 0.017982577250000003,
                    "q_75": 0.01811993141666668,
                    "std": 0.00019021834438535552
                },
                {
                    "ci_99": [
                        0.13646919236386823,
                        0.1786298843027983
                    ],
                    "max": 0.16072394400000012,
                    "mean": 0.15754953833333338,
                    "min": 0.152028269,
                    "n": 3,
                    "q_25": 0.1559623355,
                    "q_75": 0.16031017300000006,
                    "std": 0.003918717284082189
                },
                null,
                {
                    "ci_99": [
                        0.000979358327272727,
                        0.0009937266727272718
                    ],
                    "max": 0.0009937266727272718,
                    "mean": 0.000986428332727273,
                    "min": 0.000979358327272727,
                    "n": 10,
                    "q_25": 0.0009838903181818193,
                    "q_75": 0.000989117554545454,
                    "std": 4.022197046440742e-06
                },
                {
                    "ci_99": [
                        0.0023152538695652147,
                        0.0023324134347826077
                    ],
                    "max": 0.0023324134347826077,
                    "mean": 0.0023249208347826066,
                    "min": 0.0023152538695652147,
                    "n": 10,
                    "q_25": 0.0023193172499999977,
                    "q_75": 0.0023308483804347817,
                    "std": 6.218043987383495e-06
                },
                {
                    "ci_99": [
                        0.017808837333333345,
                        0.018305888666666676
                    ],
                    "max": 0.018305888666666676,
                    "mean": 0.017987141800000005,
                    "min": 0.017808837333333345,
                    "n": 10,
                    "q_25": 0.017884385000000003,
                    "q_75": 0.017975482833333334,
                    "std": 0.0001633077247767543
                },
                {
                    "ci_99": [
                        0.13700168879173066,
                        0.17617421520826923
                    ],
                    "max": 0.1595982039999999,
                    "mean": 0.15658795199999997,
                    "min": 0.15147623899999996,
                    "n": 3,
                    "q_25": 0.155082826,
                    "q_75": 0.15914380849999998,
                    "std": 0.0036335182781244836
                },
                null,
                {
                    "ci_99": [
                        4.8971937999999995e-05,
                        4.9385463000000016e-05
                    ],
                    "max": 4.9385463000000016e-05,
                    "mean": 4.917004380000001e-05,
                    "min": 4.8971937999999995e-05,
                    "n": 10,
                    "q_25": 4.910424475000008e-05,
                    "q_75": 4.9264304749999936e-05,
                    "std": 1.2674019144595592e-07
                },
                {
                    "ci_99": [
                        0.00016168039457831318,
                        0.00016457406325301227
                    ],
                    "max": 0.00016457406325301227,
                    "mean": 0.00016304496867469877,
                    "min": 0.00016168039457831318,
                    "n": 10,
                    "q_25": 0.00016246947816265063,
                    "q_75": 0.00016336256174698775,
                    "std": 8.088207247476129e-07
                },
                {
                    "ci_99": [
                        0.0014168746240773929,
                        0.001454130942589274
                    ],
                    "max": 0.0014486882142857142,
                    "mean": 0.0014355027833333337,
                    "min": 0.0014220651857142846,
                    "n": 6,
                    "q_25": 0.0014260275821428572,
                    "q_75": 0.0014453040785714299,
                    "std": 1.0690449486581098e-05
                },
                {
                    "ci_99": [
                        0.01304351718263696,
                        0.01320104541736306
                    ],
                    "max": 0.01318722,
                    "mean": 0.01312228130000001,
                    "min": 0.013058300999999994,
                    "n": 5,
                    "q_25": 0.013105358250000004,
                    "q_75": 0.013134314500000022,
                    "std": 4.18501072123508e-05
                },
                null,
                {
                    "ci_99": [
                        4.445252247667514e-05,
                        4.482702883799838e-05
                    ],
                    "max": 4.482702883799838e-05,
                    "mean": 4.4557718999151816e-05,
                    "min": 4.445252247667514e-05,
                    "n": 10,
                    "q_25": 4.448608990670054e-05,
                    "q_75": 4.45948002544529e-05,
                    "std": 1.0893867214730085e-07
                },
                {
                    "ci_99": [
                        0.0001265307042889391,
                        0.00012823579232505657
                    ],
                    "max": 0.00012823579232505657,
                    "mean": 0.00012745575756207674,
                    "min": 0.0001265307042889391,
                    "n": 10,
                    "q_25": 0.0001274157071106095,
                    "q_75": 0.00012764193227990985,
                    "std": 4.6479020390473767e-07
                },
                {
                    "ci_99": [
                        0.001079167882352941,
                        0.00111409268627451
                    ],
                    "max": 0.00111409268627451,
                    "mean": 0.0010964637363834418,
                    "min": 0.001079167882352941,
                    "n": 9,
                    "q_25": 0.0010824805686274514,
                    "q_75": 0.0011004532941176475,
                    "std": 1.2568871126191704e-05
                },
                {
                    "ci_99": [
                        0.009819042829879377,
                        0.009863469103453969
                    ],
                    "max": 0.009858026166666681,
                    "mean": 0.009841255966666674,
                    "min": 0.00982548350000001,
                    "n": 5,
                    "q_25": 0.009834847333333322,
                    "q_75": 0.009848428833333367,
                    "std": 1.1186021962657763e-05
                },
                null,
                {
                    "ci_99": [
                        4.5190668096054736e-05,
                        4.566471183533449e-05
                    ],
                    "max": 4.566471183533449e-05,
                    "mean": 4.551381432246997e-05,
                    "min": 4.5190668096054736e-05,
                    "n": 10,
                    "q_25": 4.543109476843913e-05,
                    "q_75": 4.560892259862779e-05,
                    "std": 1.4149144250528286e-07
                },
                {
                    "ci_99": [
                        0.0001387460365535248,
                        0.00014170429242819853
                    ],
                    "max": 0.00014170429242819853,
                    "mean": 0.00013995105352480414,
                    "min": 0.0001387460365535248,
                    "n": 10,
                    "q_25": 0.00013928537532637044,
                    "q_75": 0.00014033535574412549,
                    "std": 8.95508952447706e-07
                },
                {
                    "ci_99": [
                        0.0013261326666666674,
                        0.0013398278809523823
                    ],
                    "max": 0.0013398278809523823,
                    "mean": 0.0013323344338624342,
                    "min": 0.0013261326666666674,
                    "n": 9,
                    "q_25": 0.0013290614047619083,
                    "q_75": 0.001334787714285714,
                    "std": 4.336948373348461e-06
                },
                {
                    "ci_99": [
                        0.01175888571242816,
                        0.011823253167571856
                    ],
                    "max": 0.011818050400000012,
                    "mean": 0.01179106944000001,
                    "min": 0.011762608800000018,
                    "n": 5,
                    "q_25": 0.011788026799999995,
                    "q_75": 0.01179534499999999,
                    "std": 1.7695079506527094e-05
                },
                null,
                {
                    "ci_99": [
                        4.026906365655072e-05,
                        4.185897631384157e-05
                    ],
                    "max": 4.185897631384157e-05,
                    "mean": 4.1153235899333817e-05,
                    "min": 4.026906365655072e-05,
                    "n": 10,
                    "q_25": 4.1087958549222847e-05,
                    "q_75": 4.1393495373797106e-05,
                    "std": 4.770365632459607e-07
                },
                {
                    "ci_99": [
                        0.00010980891472868211,
                        0.00011075054263565896
                    ],
                    "max": 0.00011075054263565896,
                    "mean": 0.00011037557325581392,
                    "min": 0.00010980891472868211,
                    "n": 10,
                    "q_25": 0.00011033857558139541,
                    "q_75": 0.00011049762112403074,
                    "std": 2.384599145272131e-07
                },
                {
                    "ci_99": [
                        0.0009867401698113207,
                        0.0010001308490566034
                    ],
                    "max": 0.0010001308490566034,
                    "mean": 0.0009917524245283019,
                    "min": 0.0009867401698113207,
                    "n": 10,
                    "q_25": 0.0009882019575471678,
                    "q_75": 0.0009939234716981145,
                    "std": 3.926269382545402e-06
                },
                {
                    "ci_99": [
                        0.008428616314070254,
                        0.008598037219263064
                    ],
                    "max": 0.00856368633333332,
                    "mean": 0.008513326766666659,
                    "min": 0.008458840000000004,
                    "n": 5,
                    "q_25": 0.008473196833333327,
                    "q_75": 0.008547978166666673,
                    "std": 4.1008035507226504e-05
                },
                null
            ]
        },
        "benchmarks.Histogram2D.time_histogram2d_weights": {
            "params": [
                [
                    "False",
                    "True"
                ],
                [
                    "'>i4'",
                    "'<f4'",
                    "'>f8'",
                    "'<f8'"
                ],
                [
                    "1000.0",
                    "10000.0",
                    "100000.0",
                    "1000000.0",
                    "10000000.0"
                ]
            ],
            "result": [
                0.000923263533333334,
                0.0019325813703703714,
                0.013750150625000013,
                0.12202133500000012,
                1.4762900960000003,
                0.0009919691636363637,
                0.002101775557692305,
                0.015192782666666682,
                0.138547835,
                1.6634984679999998,
                0.00098130128,
                0.0023601233541666643,
                0.01850758916666667,
                0.16367471100000008,
                1.900137979,
                0.0009835237547169825,
                0.002332131818181823,
                0.01815441699999998,
                0.1597088470000001,
                1.82885171,
                5.260005800000006e-05,
                0.00019325311524822703,
                0.0017693156451612907,
                0.015564162500000006,
                0.15496482499999997,
                4.498959752066115e-05,
                0.00013434938676844775,
                0.0012205604333333335,
                0.010725301333333333,
                0.10623710499999994,
                4.768683000000001e-05,
                0.0001598741919504643,
                0.001531171666666669,
                0.013711434500000008,
                0.13523081400000025,
                4.192159718969553e-05,
                0.0001082161200000001,
                0.0010235036538461528,
                0.008684110999999994,
                0.08600564699999991
            ],
            "stats": [
                {
                    "ci_99": [
                        0.0009170596499999998,
                        0.0009272409666666666
                    ],
                    "max": 0.0009272409666666666,
                    "mean": 0.0009226993783333337,
                    "min": 0.0009170596499999998,
                    "n": 10,
                    "q_25": 0.0009201661791666662,
                    "q_75": 0.0009247188625000004,
                    "std": 3.2579067824301276e-06
                },
                {
                    "ci_99": [
                        0.0019220074444444434,
                        0.0019493026296296266
                    ],
                    "max": 0.0019493026296296266,
                    "mean": 0.0019341885740740735,
                    "min": 0.0019220074444444434,
                    "n": 10,
                    "q_25": 0.0019281055555555552,
                    "q_75": 0.0019408845185185158,
                    "std": 8.389079855993516e-06
                },
                {
                    "ci_99": [
                        0.013668907499999994,
                        0.014432162499999984
                    ],
                    "max": 0.014432162499999984,
                    "mean": 0.013877031225000003,
                    "min": 0.013668907499999994,
                    "n": 10,
                    "q_25": 0.013729258687500016,
                    "q_75": 0.01380934625,
                    "std": 0.0002757751324851755
                },
                {
                    "ci_99": [
                        0.1113489016810762,
                        0.13184095431892387
                    ],
                    "max": 0.12360154200000006,
                    "mean": 0.12159492800000005,
                    "min": 0.11916190699999996,
                    "n": 3,
                    "q_25": 0.12059162100000004,
                    "q_75": 0.12281143850000009,
                    "std": 0.001837381638916874
                },
                null,
                {
                    "ci_99": [
                        0.000984617381818181,
                        0.0009977206909090916
                    ],
                    "max": 0.0009977206909090916,
                    "mean": 0.0009903762581818178,
                    "min": 0.000984617381818181,
                    "n": 10,
                    "q_25": 0.0009857092818181812,
                    "q_75": 0.0009937651545454547,
                    "std": 4.513273991831833e-06
                },
                {
                    "ci_99": [
                        0.0020889564230769206,
                        0.002111451769230768
                    ],
                    "max": 0.002111451769230768,
                    "mean": 0.0021006072000000005,
                    "min": 0.0020889564230769206,
                    "n": 10,
                    "q_25": 0.0020931791634615417,
                    "q_75": 0.0021084258557692312,
                    "std": 8.589608330299798e-06
                },
                {
                    "ci_99": [
                        0.015034086333333363,
                        0.016040556999999993
                    ],
                    "max": 0.016040556999999993,
                    "mean": 0.015323116733333345,
                    "min": 0.015034086333333363,
                    "n": 10,
                    "q_25": 0.015103018250000025,
                    "q_75": 0.015289957166666682,
                    "std": 0.00034614537802392045
                },
                {
                    "ci_99": [
                        0.1289558403466193,
                        0.1460129469867141
                    ],
                    "max": 0.13867373700000019,
                    "mean": 0.13748439366666673,
                    "min": 0.13523160899999997,
                    "n": 3,
                    "q_25": 0.136889722,
                    "q_75": 0.1386107860000001,
                    "std": 0.0015937883368832512
                },
                null,
                {
                    "ci_99": [
                        0.0009778872400000016,
                        0.0009825390020752472
                    ],
                    "max": 0.0009821250400000004,
                    "mean": 0.0009809951200000005,
                    "min": 0.0009778872400000016,
                    "n": 7,
                    "q_25": 0.0009809852600000007,
                    "q_75": 0.00098184088,
                    "std": 1.3481947084469765e-06
                },
                {
                    "ci_99": [
                        0.002270237833333332,
                        0.002374494333333333
                    ],
                    "max": 0.002374494333333333,
                    "mean": 0.002346614583333333,
                    "min": 0.002270237833333332,
                    "n": 10,
                    "q_25": 0.002352898593750001,
                    "q_75": 0.0023649822708333365,
                    "std": 3.44246740160365e-05
                },
                {
                    "ci_99": [
                        0.018315646666666668,
                        0.018960194666666652
                    ],
                    "max": 0.018960194666666652,
                    "mean": 0.018545952533333333,
                    "min": 0.018315646666666668,
                    "n": 10,
                    "q_25": 0.018422873750000023,
                    "q_75": 0.018572555583333327,
                    "std": 0.0001892988831998031
                },
                {
                    "ci_99": [
                        0.1409412490902006,
                        0.1819347235764663
                    ],
                    "max": 0.16455950799999997,
                    "mean": 0.16143798633333337,
                    "min": 0.15607974000000002,
                    "n": 3,
                    "q_25": 0.15987722550000005,
                    "q_75": 0.16411710950000002,
                    "std": 0.003806031989645935
                },
                null,
                {
                    "ci_99": [
                        0.0009774629622641491,
                        0.001018142339622641
                    ],
                    "max": 0.001018142339622641,
                    "mean": 0.000986056916981132,
                    "min": 0.0009774629622641491,
                    "n": 10,
                    "q_25": 0.0009812443018867923,
                    "q_75": 0.000985669995283018,
                    "std": 1.1055373153767431e-05
                },
                {
                    "ci_99": [
                        0.002317592,
                        0.0023465619545454575
                    ],
                    "max": 0.0023465619545454575,
                    "mean": 0.0023313249909090914,
                    "min": 0.002317592,
                    "n": 10,
                    "q_25": 0.0023233163636363643,
                    "q_75": 0.0023381226477272726,
                    "std": 1.0021325779313764e-05
                },
                {
                    "ci_99": [
                        0.018109055000000002,
                        0.018630616999999978
                    ],
                    "max": 0.018630616999999978,
                    "mean": 0.018237510733333337,
                    "min": 0.018109055000000002,
                    "n": 10,
                    "q_25": 0.018121721000000018,
                    "q_75": 0.01817374716666668,
                    "std": 0.00019382500249541366
                },
                {
                    "ci_99": [
                        0.13987246786301719,
                        0.1750405874703163
                    ],
                    "max": 0.15985405800000008,
                    "mean": 0.15745652766666673,
                    "min": 0.15280667800000003,
                    "n": 3,
                    "q_25": 0.15625776250000006,
                    "q_75": 0.1597814525000001,
                    "std": 0.00328847462111545
                },
                null,
                {
                    "ci_99": [
                        5.234632300000008e-05,
                        5.2869249000000006e-05
                    ],
                    "max": 5.2869249000000006e-05,
                    "mean": 5.260504720000003e-05,
                    "min": 5.234632300000008e-05,
                    "n": 10,
                    "q_25": 5.253228574999999e-05,
                    "q_75": 5.270648725000002e-05,
                    "std": 1.6542025085387916e-07
                },
                {
                    "ci_99": [
                        0.00018956106382978703,
                        0.00019614010283687956
                    ],
                    "max": 0.00019614010283687956,
                    "mean": 0.0001932747964539007,
                    "min": 0.00018956106382978703,
                    "n": 10,
                    "q_25": 0.00019208885638297873,
                    "q_75": 0.0001945478528368795,
                    "std": 1.9338974716246225e-06
                },
                {
                    "ci_99": [
                        0.001711911064516134,
                        0.001773603451612901
                    ],
                    "max": 0.001773603451612901,
                    "mean": 0.001753818978494624,
                    "min": 0.001711911064516134,
                    "n": 9,
                    "q_25": 0.0017323914516129046,
                    "q_75": 0.0017699167419354775,
                    "std": 2.3873217035437982e-05
                },
                {
                    "ci_99": [
                        0.015496527490989592,
                        0.015661818134010436
                    ],
                    "max": 0.015634831750000022,
                    "mean": 0.015579172812500014,
                    "min": 0.015553534500000021,
                    "n": 4,
                    "q_25": 0.015555799312500021,
                    "q_75": 0.015587535999999999,
                    "std": 3.286955388462642e-05
                },
                null,
                {
                    "ci_99": [
                        4.463760495867772e-05,
                        4.5065878512396676e-05
                    ],
                    "max": 4.5065878512396676e-05,
                    "mean": 4.491623429752062e-05,
                    "min": 4.463760495867772e-05,
                    "n": 10,
                    "q_25": 4.482528739669409e-05,
                    "q_75": 4.502021528925623e-05,
                    "std": 1.432488972363323e-07
                },
                {
                    "ci_99": [
                        0.0001330935419847329,
                        0.0001355074554707381
                    ],
                    "max": 0.0001355074554707381,
                    "mean": 0.00013441258193384227,
                    "min": 0.0001330935419847329,
                    "n": 10,
                    "q_25": 0.00013405402480916033,
                    "q_75": 0.00013483423536895687,
                    "std": 6.669013476094649e-07
                },
                {
                    "ci_99": [
                        0.0012168271999999985,
                        0.0012264785111111114
                    ],
                    "max": 0.0012264785111111114,
                    "mean": 0.0012212064311111113,
                    "min": 0.0012168271999999985,
                    "n": 10,
                    "q_25": 0.0012181253888888892,
                    "q_75": 0.001224566566666667,
                    "std": 3.5312320546270252e-06
                },
                {
                    "ci_99": [
                        0.010706083016534806,
                        0.0107442794834652
                    ],
                    "max": 0.010733426555555573,
                    "mean": 0.010725181250000002,
                    "min": 0.010716695777777773,
                    "n": 4,
                    "q_25": 0.010719974861111108,
                    "q_75": 0.010730507722222227,
                    "std": 6.630634326390968e-06
                },
                null,
                {
                    "ci_99": [
                        4.71346045454546e-05,
                        4.838748818181824e-05
                    ],
                    "max": 4.838748818181824e-05,
                    "mean": 4.7719602636363644e-05,
                    "min": 4.71346045454546e-05,
                    "n": 10,
                    "q_25": 4.7636623409090805e-05,
                    "q_75": 4.784295772727272e-05,
                    "std": 3.0118340799801337e-07
                },
                {
                    "ci_99": [
                        0.0001561818823529413,
                        0.00016413560990712075
                    ],
                    "max": 0.00016413560990712075,
                    "mean": 0.00015954974396284832,
                    "min": 0.0001561818823529413,
                    "n": 10,
                    "q_25": 0.00015732936455108368,
                    "q_75": 0.0001601122801857585,
                    "std": 2.4702230080069115e-06
                },
                {
                    "ci_99": [
                        0.0015277477222222194,
                        0.0015416320555555567
                    ],
                    "max": 0.0015416320555555567,
                    "mean": 0.0015321852444444442,
                    "min": 0.0015277477222222194,
                    "n": 10,
                    "q_25": 0.001529227583333335,
                    "q_75": 0.001534413791666665,
                    "std": 4.141547316146783e-06
                },
                {
                    "ci_99": [
                        0.013665415759306094,
                        0.013756871440693902
                    ],
                    "max": 0.01374620800000001,
                    "mean": 0.013711143599999998,
                    "min": 0.013673163749999995,
                    "n": 5,
                    "q_25": 0.013702492250000003,
                    "q_75": 0.013722419499999972,
                    "std": 2.3975227022180155e-05
                },
                null,
                {
                    "ci_99": [
                        4.158165573770497e-05,
                        4.209275409836068e-05
                    ],
                    "max": 4.209275409836068e-05,
                    "mean": 4.1862379078844656e-05,
                    "min": 4.158165573770497e-05,
                    "n": 10,
                    "q_25": 4.168742642466822e-05,
                    "q_75": 4.198894359875101e-05,
                    "std": 1.8244637444442484e-07
                },
                {
                    "ci_99": [
                        0.00010755868266666665,
                        0.00010836481466666663
                    ],
                    "max": 0.00010836481466666663,
                    "mean": 0.00010804375600000002,
                    "min": 0.00010755868266666665,
                    "n": 8,
                    "q_25": 0.00010777851566666682,
                    "q_75": 0.00010827311799999995,
                    "std": 3.0247633415451563e-07
                },
                {
                    "ci_99": [
                        0.001018854788461536,
                        0.0010271435000000005
                    ],
                    "max": 0.0010271435000000005,
                    "mean": 0.001023228012820513,
                    "min": 0.001018854788461536,
                    "n": 9,
                    "q_25": 0.0010203359038461544,
                    "q_75": 0.0010266422692307687,
                    "std": 3.1409063156826455e-06
                },
                {
                    "ci_99": [
                        0.008625718222321959,
                        0.008794183999999983
                    ],
                    "max": 0.008794183999999983,
                    "mean": 0.008705297566666667,
                    "min": 0.008660622000000026,
                    "n": 5,
                    "q_25": 0.008683444000000004,
                    "q_75": 0.008704126833333325,
                    "std": 4.6528537237736014e-05
                },
                null
            ]
        }
    },
    "started_at": {
        "benchmarks.Histogram1D.time_histogram1d": 1539648548000,
        "benchmarks.Histogram1D.time_histogram1d_weights": 1539648663000,
        "benchmarks.Histogram2D.time_histogram2d": 1539648779000,
        "benchmarks.Histogram2D.time_histogram2d_weights": 1539648908000
    },
    "version": 1
}